Workbook
Name LanguageID: 'Data'!$G$2
Name TranslationHeaders: 'Translation'!$F$1:$G$31

Sheet DRE Acumulado
A1: =Translation!$A$22 -> DRE YAMAHA BMI - Acumulado
A2: =Translation!$A$20&Data!D1 -> Concessionário: %%=$RecordSet.#4 | C2: =Translation!$A$19&Data!D3 -> Localização: %%=$RecordSet.#8 | H2: =Translation!$A$21 -> Período: | I2: =VLOOKUP(Data!D6,Data!H1:I12,2,FALSE)&" "&Data!E6 -> #N/A
A3: =Translation!A1 -> VENDA DE NOVOS | O3: VENDA NOVOS
A4: =Translation!A35 -> LINHA SCOOTER <200 cc | B4: =Translation!$G$32 -> CONTA | C4: =Translation!$G$12 -> UNIDADES | D4: =Translation!$G$11 -> RECEITA (SEM IMPOSTOS) | E4: =Translation!$G$33 -> UNIDADES DEVOLVIDAS | F4: =Translation!$G$14 -> DEVOLUÇÃO DE VENDAS | G4: =Translation!$G$3 -> ABAT. E DESCONTO | H4: =Translation!$G$9 -> RECEITA LÍQUIDA | I4: =Translation!$G$2 -> CUSTO | J4: =Translation!$G$5 -> LUCRO BRUTO | O4: LINHA SCOOTER <200 cc | P4: =Translation!$G$32 -> CONTA | Q4: UNITS | R4: SALES | S4: URETURN | T4: SC | U4: DISC | V4: NS | W4: COS | X4: GP
A5: =Translation!A36 -> NEO 125 | B5: A1000 | C5: =VLOOKUP(Q5,Data!$B:$E,4,FALSE) -> #N/A | D5: =VLOOKUP(R5,Data!$B:$E,4,FALSE) -> #N/A | E5: =VLOOKUP(S5,Data!$B:$E,4,FALSE) -> #N/A | F5: =VLOOKUP(T5,Data!$B:$E,4,FALSE) -> #N/A | G5: =VLOOKUP(U5,Data!$B:$E,4,FALSE) -> #N/A | H5: =VLOOKUP(V5,Data!$B:$E,4,FALSE) -> #N/A | I5: =VLOOKUP(W5,Data!$B:$E,4,FALSE) -> #N/A | J5: =VLOOKUP(X5,Data!$B:$E,4,FALSE) -> #N/A | O5: NEO 125 | P5: A1000 | Q5: A1000.1 | R5: A1000.2 | S5: A1000.8 | T5: A1000.3 | U5: A1000.4 | V5: A1000.5 | W5: A1000.6 | X5: A1000.7
A6: =Translation!A37 -> NMAX 160 ABS | B6: A1010 | C6: =VLOOKUP(Q6,Data!$B:$E,4,FALSE) -> #N/A | D6: =VLOOKUP(R6,Data!$B:$E,4,FALSE) -> #N/A | E6: =VLOOKUP(S6,Data!$B:$E,4,FALSE) -> #N/A | F6: =VLOOKUP(T6,Data!$B:$E,4,FALSE) -> #N/A | G6: =VLOOKUP(U6,Data!$B:$E,4,FALSE) -> #N/A | H6: =VLOOKUP(V6,Data!$B:$E,4,FALSE) -> #N/A | I6: =VLOOKUP(W6,Data!$B:$E,4,FALSE) -> #N/A | J6: =VLOOKUP(X6,Data!$B:$E,4,FALSE) -> #N/A | O6: NMAX 160 ABS | P6: A1010 | Q6: A1010.1 | R6: A1010.2 | S6: A1010.8 | T6: A1010.3 | U6: A1010.4 | V6: A1010.5 | W6: A1010.6 | X6: A1010.7
A7: =Translation!A38 -> LINHA SCOOTER >200 cc | B7: =Translation!$G$32 -> CONTA | C7: =Translation!$G$12 -> UNIDADES | D7: =Translation!$G$11 -> RECEITA (SEM IMPOSTOS) | E7: =Translation!$G$33 -> UNIDADES DEVOLVIDAS | F7: =Translation!$G$14 -> DEVOLUÇÃO DE VENDAS | G7: =Translation!$G$3 -> ABAT. E DESCONTO | H7: =Translation!$G$9 -> RECEITA LÍQUIDA | I7: =Translation!$G$2 -> CUSTO | J7: =Translation!$G$5 -> LUCRO BRUTO | O7: LINHA SCOOTER >200 cc | P7: =Translation!$G$32 -> CONTA | Q7: UNITS | R7: SALES | S7: URETURN | T7: SC | U7: DISC | V7: NS | W7: COS | X7: GP
A8: =Translation!A39 -> TMAX 530 | B8: A1020 | C8: =VLOOKUP(Q8,Data!$B:$E,4,FALSE) -> #N/A | D8: =VLOOKUP(R8,Data!$B:$E,4,FALSE) -> #N/A | E8: =VLOOKUP(S8,Data!$B:$E,4,FALSE) -> #N/A | F8: =VLOOKUP(T8,Data!$B:$E,4,FALSE) -> #N/A | G8: =VLOOKUP(U8,Data!$B:$E,4,FALSE) -> #N/A | H8: =VLOOKUP(V8,Data!$B:$E,4,FALSE) -> #N/A | I8: =VLOOKUP(W8,Data!$B:$E,4,FALSE) -> #N/A | J8: =VLOOKUP(X8,Data!$B:$E,4,FALSE) -> #N/A | O8: TMAX 530 | P8: A1020 | Q8: A1020.1 | R8: A1020.2 | S8: A1020.8 | T8: A1020.3 | U8: A1020.4 | V8: A1020.5 | W8: A1020.6 | X8: A1020.7
A9: X MAX ABS | B9: A1021 | C9: =VLOOKUP(Q9,Data!$B:$E,4,FALSE) -> #N/A | D9: =VLOOKUP(R9,Data!$B:$E,4,FALSE) -> #N/A | E9: =VLOOKUP(S9,Data!$B:$E,4,FALSE) -> #N/A | F9: =VLOOKUP(T9,Data!$B:$E,4,FALSE) -> #N/A | G9: =VLOOKUP(U9,Data!$B:$E,4,FALSE) -> #N/A | H9: =VLOOKUP(V9,Data!$B:$E,4,FALSE) -> #N/A | I9: =VLOOKUP(W9,Data!$B:$E,4,FALSE) -> #N/A | J9: =VLOOKUP(X9,Data!$B:$E,4,FALSE) -> #N/A | O9: X MAX ABS | P9: A1021 | Q9: A1021.1 | R9: A1021.2 | S9: A1021.8 | T9: A1021.3 | U9: A1021.4 | V9: A1021.5 | W9: A1021.6 | X9: A1021.7
A10: NEOS CONNECTED | B10: A1022 | C10: =VLOOKUP(Q10,Data!$B:$E,4,FALSE) -> #N/A | D10: =VLOOKUP(R10,Data!$B:$E,4,FALSE) -> #N/A | E10: =VLOOKUP(S10,Data!$B:$E,4,FALSE) -> #N/A | F10: =VLOOKUP(T10,Data!$B:$E,4,FALSE) -> #N/A | G10: =VLOOKUP(U10,Data!$B:$E,4,FALSE) -> #N/A | H10: =VLOOKUP(V10,Data!$B:$E,4,FALSE) -> #N/A | I10: =VLOOKUP(W10,Data!$B:$E,4,FALSE) -> #N/A | J10: =VLOOKUP(X10,Data!$B:$E,4,FALSE) -> #N/A | O10: NEOS CONNECTED | P10: A1022 | Q10: A1022.1 | R10: A1022.2 | S10: A1022.8 | T10: A1022.3 | U10: A1022.4 | V10: A1022.5 | W10: A1022.6 | X10: A1022.7
A11: =Translation!A40 -> TOTAL DE VENDAS - SCOOTER | B11: A1030 | C11: =VLOOKUP(Q11,Data!$B:$E,4,FALSE) -> #N/A | D11: =VLOOKUP(R11,Data!$B:$E,4,FALSE) -> #N/A | E11: =VLOOKUP(S11,Data!$B:$E,4,FALSE) -> #N/A | F11: =VLOOKUP(T11,Data!$B:$E,4,FALSE) -> #N/A | G11: =VLOOKUP(U11,Data!$B:$E,4,FALSE) -> #N/A | H11: =VLOOKUP(V11,Data!$B:$E,4,FALSE) -> #N/A | I11: =VLOOKUP(W11,Data!$B:$E,4,FALSE) -> #N/A | J11: =VLOOKUP(X11,Data!$B:$E,4,FALSE) -> #N/A | O11: TOTAL DE VENDAS - SCOOTER | P11: A1030 | Q11: A1030.1 | R11: A1030.2 | S11: A1030.8 | T11: A1030.3 | U11: A1030.4 | V11: A1030.5 | W11: A1030.6 | X11: A1030.7
A12: =Translation!A41 -> LINHA OFF ROAD | B12: =Translation!$G$32 -> CONTA | C12: =Translation!$G$12 -> UNIDADES | D12: =Translation!$G$11 -> RECEITA (SEM IMPOSTOS) | E12: =Translation!$G$33 -> UNIDADES DEVOLVIDAS | F12: =Translation!$G$14 -> DEVOLUÇÃO DE VENDAS | G12: =Translation!$G$3 -> ABAT. E DESCONTO | H12: =Translation!$G$9 -> RECEITA LÍQUIDA | I12: =Translation!$G$2 -> CUSTO | J12: =Translation!$G$5 -> LUCRO BRUTO | O12: LINHA OFF ROAD | P12: =Translation!$G$32 -> CONTA | Q12: UNITS | R12: SALES | S12: URETURN | T12: SC | U12: DISC | V12: NS | W12: COS | X12: GP
A13: =Translation!A42 -> TTR 230 | B13: A1040 | C13: =VLOOKUP(Q13,Data!$B:$E,4,FALSE) -> #N/A | D13: =VLOOKUP(R13,Data!$B:$E,4,FALSE) -> #N/A | E13: =VLOOKUP(S13,Data!$B:$E,4,FALSE) -> #N/A | F13: =VLOOKUP(T13,Data!$B:$E,4,FALSE) -> #N/A | G13: =VLOOKUP(U13,Data!$B:$E,4,FALSE) -> #N/A | H13: =VLOOKUP(V13,Data!$B:$E,4,FALSE) -> #N/A | I13: =VLOOKUP(W13,Data!$B:$E,4,FALSE) -> #N/A | J13: =VLOOKUP(X13,Data!$B:$E,4,FALSE) -> #N/A | O13: TTR 230 | P13: A1040 | Q13: A1040.1 | R13: A1040.2 | S13: A1040.8 | T13: A1040.3 | U13: A1040.4 | V13: A1040.5 | W13: A1040.6 | X13: A1040.7
A14: YZ 85LW | B14: A1045 | C14: =VLOOKUP(Q14,Data!$B:$E,4,FALSE) -> #N/A | D14: =VLOOKUP(R14,Data!$B:$E,4,FALSE) -> #N/A | E14: =VLOOKUP(S14,Data!$B:$E,4,FALSE) -> #N/A | F14: =VLOOKUP(T14,Data!$B:$E,4,FALSE) -> #N/A | G14: =VLOOKUP(U14,Data!$B:$E,4,FALSE) -> #N/A | H14: =VLOOKUP(V14,Data!$B:$E,4,FALSE) -> #N/A | I14: =VLOOKUP(W14,Data!$B:$E,4,FALSE) -> #N/A | J14: =VLOOKUP(X14,Data!$B:$E,4,FALSE) -> #N/A | O14: YZ 85LW | P14: A1045 | Q14: A1045.1 | R14: A1045.2 | S14: A1045.8 | T14: A1045.3 | U14: A1045.4 | V14: A1045.5 | W14: A1045.6 | X14: A1045.7
A15: =Translation!A44 -> YZ 250 | B15: A1050 | C15: =VLOOKUP(Q15,Data!$B:$E,4,FALSE) -> #N/A | D15: =VLOOKUP(R15,Data!$B:$E,4,FALSE) -> #N/A | E15: =VLOOKUP(S15,Data!$B:$E,4,FALSE) -> #N/A | F15: =VLOOKUP(T15,Data!$B:$E,4,FALSE) -> #N/A | G15: =VLOOKUP(U15,Data!$B:$E,4,FALSE) -> #N/A | H15: =VLOOKUP(V15,Data!$B:$E,4,FALSE) -> #N/A | I15: =VLOOKUP(W15,Data!$B:$E,4,FALSE) -> #N/A | J15: =VLOOKUP(X15,Data!$B:$E,4,FALSE) -> #N/A | O15: YZ 250 | P15: A1050 | Q15: A1050.1 | R15: A1050.2 | S15: A1050.8 | T15: A1050.3 | U15: A1050.4 | V15: A1050.5 | W15: A1050.6 | X15: A1050.7
A16: =Translation!A45 -> YZ 250F | B16: A1060 | C16: =VLOOKUP(Q16,Data!$B:$E,4,FALSE) -> #N/A | D16: =VLOOKUP(R16,Data!$B:$E,4,FALSE) -> #N/A | E16: =VLOOKUP(S16,Data!$B:$E,4,FALSE) -> #N/A | F16: =VLOOKUP(T16,Data!$B:$E,4,FALSE) -> #N/A | G16: =VLOOKUP(U16,Data!$B:$E,4,FALSE) -> #N/A | H16: =VLOOKUP(V16,Data!$B:$E,4,FALSE) -> #N/A | I16: =VLOOKUP(W16,Data!$B:$E,4,FALSE) -> #N/A | J16: =VLOOKUP(X16,Data!$B:$E,4,FALSE) -> #N/A | O16: YZ 250F | P16: A1060 | Q16: A1060.1 | R16: A1060.2 | S16: A1060.8 | T16: A1060.3 | U16: A1060.4 | V16: A1060.5 | W16: A1060.6 | X16: A1060.7
A17: =Translation!A46 -> YZ 250FX | B17: A1070 | C17: =VLOOKUP(Q17,Data!$B:$E,4,FALSE) -> #N/A | D17: =VLOOKUP(R17,Data!$B:$E,4,FALSE) -> #N/A | E17: =VLOOKUP(S17,Data!$B:$E,4,FALSE) -> #N/A | F17: =VLOOKUP(T17,Data!$B:$E,4,FALSE) -> #N/A | G17: =VLOOKUP(U17,Data!$B:$E,4,FALSE) -> #N/A | H17: =VLOOKUP(V17,Data!$B:$E,4,FALSE) -> #N/A | I17: =VLOOKUP(W17,Data!$B:$E,4,FALSE) -> #N/A | J17: =VLOOKUP(X17,Data!$B:$E,4,FALSE) -> #N/A | O17: YZ 250FX | P17: A1070 | Q17: A1070.1 | R17: A1070.2 | S17: A1070.8 | T17: A1070.3 | U17: A1070.4 | V17: A1070.5 | W17: A1070.6 | X17: A1070.7
A18: YZ 250X | B18: A1075 | C18: =VLOOKUP(Q18,Data!$B:$E,4,FALSE) -> #N/A | D18: =VLOOKUP(R18,Data!$B:$E,4,FALSE) -> #N/A | E18: =VLOOKUP(S18,Data!$B:$E,4,FALSE) -> #N/A | F18: =VLOOKUP(T18,Data!$B:$E,4,FALSE) -> #N/A | G18: =VLOOKUP(U18,Data!$B:$E,4,FALSE) -> #N/A | H18: =VLOOKUP(V18,Data!$B:$E,4,FALSE) -> #N/A | I18: =VLOOKUP(W18,Data!$B:$E,4,FALSE) -> #N/A | J18: =VLOOKUP(X18,Data!$B:$E,4,FALSE) -> #N/A | O18: YZ 250X | P18: A1075 | Q18: A1075.1 | R18: A1075.2 | S18: A1075.8 | T18: A1075.3 | U18: A1075.4 | V18: A1075.5 | W18: A1075.6 | X18: A1075.7
A19: =Translation!A48 -> YZ 450F | B19: A1080 | C19: =VLOOKUP(Q19,Data!$B:$E,4,FALSE) -> #N/A | D19: =VLOOKUP(R19,Data!$B:$E,4,FALSE) -> #N/A | E19: =VLOOKUP(S19,Data!$B:$E,4,FALSE) -> #N/A | F19: =VLOOKUP(T19,Data!$B:$E,4,FALSE) -> #N/A | G19: =VLOOKUP(U19,Data!$B:$E,4,FALSE) -> #N/A | H19: =VLOOKUP(V19,Data!$B:$E,4,FALSE) -> #N/A | I19: =VLOOKUP(W19,Data!$B:$E,4,FALSE) -> #N/A | J19: =VLOOKUP(X19,Data!$B:$E,4,FALSE) -> #N/A | O19: YZ 450F | P19: A1080 | Q19: A1080.1 | R19: A1080.2 | S19: A1080.8 | T19: A1080.3 | U19: A1080.4 | V19: A1080.5 | W19: A1080.6 | X19: A1080.7
A20: YZ 450 FX | B20: A1085 | C20: =VLOOKUP(Q20,Data!$B:$E,4,FALSE) -> #N/A | D20: =VLOOKUP(R20,Data!$B:$E,4,FALSE) -> #N/A | E20: =VLOOKUP(S20,Data!$B:$E,4,FALSE) -> #N/A | F20: =VLOOKUP(T20,Data!$B:$E,4,FALSE) -> #N/A | G20: =VLOOKUP(U20,Data!$B:$E,4,FALSE) -> #N/A | H20: =VLOOKUP(V20,Data!$B:$E,4,FALSE) -> #N/A | I20: =VLOOKUP(W20,Data!$B:$E,4,FALSE) -> #N/A | J20: =VLOOKUP(X20,Data!$B:$E,4,FALSE) -> #N/A | O20: YZ 450 FX | P20: A1085 | Q20: A1085.1 | R20: A1085.2 | S20: A1085.8 | T20: A1085.3 | U20: A1085.4 | V20: A1085.5 | W20: A1085.6 | X20: A1085.7
A21: =Translation!A50 -> WR 250F | B21: A1090 | C21: =VLOOKUP(Q21,Data!$B:$E,4,FALSE) -> #N/A | D21: =VLOOKUP(R21,Data!$B:$E,4,FALSE) -> #N/A | E21: =VLOOKUP(S21,Data!$B:$E,4,FALSE) -> #N/A | F21: =VLOOKUP(T21,Data!$B:$E,4,FALSE) -> #N/A | G21: =VLOOKUP(U21,Data!$B:$E,4,FALSE) -> #N/A | H21: =VLOOKUP(V21,Data!$B:$E,4,FALSE) -> #N/A | I21: =VLOOKUP(W21,Data!$B:$E,4,FALSE) -> #N/A | J21: =VLOOKUP(X21,Data!$B:$E,4,FALSE) -> #N/A | O21: WR 250F | P21: A1090 | Q21: A1090.1 | R21: A1090.2 | S21: A1090.8 | T21: A1090.3 | U21: A1090.4 | V21: A1090.5 | W21: A1090.6 | X21: A1090.7
A22: WR 450F | B22: A1095 | C22: =VLOOKUP(Q22,Data!$B:$E,4,FALSE) -> #N/A | D22: =VLOOKUP(R22,Data!$B:$E,4,FALSE) -> #N/A | E22: =VLOOKUP(S22,Data!$B:$E,4,FALSE) -> #N/A | F22: =VLOOKUP(T22,Data!$B:$E,4,FALSE) -> #N/A | G22: =VLOOKUP(U22,Data!$B:$E,4,FALSE) -> #N/A | H22: =VLOOKUP(V22,Data!$B:$E,4,FALSE) -> #N/A | I22: =VLOOKUP(W22,Data!$B:$E,4,FALSE) -> #N/A | J22: =VLOOKUP(X22,Data!$B:$E,4,FALSE) -> #N/A | O22: WR 450F | P22: A1095 | Q22: A1095.1 | R22: A1095.2 | S22: A1095.8 | T22: A1095.3 | U22: A1095.4 | V22: A1095.5 | W22: A1095.6 | X22: A1095.7
A23: =Translation!A52 -> TOTAL DE VENDAS - LINHA OFF ROAD | B23: A1100 | C23: =VLOOKUP(Q23,Data!$B:$E,4,FALSE) -> #N/A | D23: =VLOOKUP(R23,Data!$B:$E,4,FALSE) -> #N/A | E23: =VLOOKUP(S23,Data!$B:$E,4,FALSE) -> #N/A | F23: =VLOOKUP(T23,Data!$B:$E,4,FALSE) -> #N/A | G23: =VLOOKUP(U23,Data!$B:$E,4,FALSE) -> #N/A | H23: =VLOOKUP(V23,Data!$B:$E,4,FALSE) -> #N/A | I23: =VLOOKUP(W23,Data!$B:$E,4,FALSE) -> #N/A | J23: =VLOOKUP(X23,Data!$B:$E,4,FALSE) -> #N/A | O23: TOTAL DE VENDAS - LINHA OFF ROAD | P23: A1100 | Q23: A1100.1 | R23: A1100.2 | S23: A1100.8 | T23: A1100.3 | U23: A1100.4 | V23: A1100.5 | W23: A1100.6 | X23: A1100.7
A24: =Translation!A53 -> LINHA 125 cc | B24: =Translation!$G$32 -> CONTA | C24: =Translation!$G$12 -> UNIDADES | D24: =Translation!$G$11 -> RECEITA (SEM IMPOSTOS) | E24: =Translation!$G$33 -> UNIDADES DEVOLVIDAS | F24: =Translation!$G$14 -> DEVOLUÇÃO DE VENDAS | G24: =Translation!$G$3 -> ABAT. E DESCONTO | H24: =Translation!$G$9 -> RECEITA LÍQUIDA | I24: =Translation!$G$2 -> CUSTO | J24: =Translation!$G$5 -> LUCRO BRUTO | O24: LINHA 125 cc | P24: =Translation!$G$32 -> CONTA | Q24: UNITS | R24: SALES | S24: URETURN | T24: SC | U24: DISC | V24: NS | W24: COS | X24: GP
A25: =Translation!A54 -> FACTOR YBR 125i ED | B25: A1110 | C25: =VLOOKUP(Q25,Data!$B:$E,4,FALSE) -> #N/A | D25: =VLOOKUP(R25,Data!$B:$E,4,FALSE) -> #N/A | E25: =VLOOKUP(S25,Data!$B:$E,4,FALSE) -> #N/A | F25: =VLOOKUP(T25,Data!$B:$E,4,FALSE) -> #N/A | G25: =VLOOKUP(U25,Data!$B:$E,4,FALSE) -> #N/A | H25: =VLOOKUP(V25,Data!$B:$E,4,FALSE) -> #N/A | I25: =VLOOKUP(W25,Data!$B:$E,4,FALSE) -> #N/A | J25: =VLOOKUP(X25,Data!$B:$E,4,FALSE) -> #N/A | O25: FACTOR YBR 125i ED | P25: A1110 | Q25: A1110.1 | R25: A1110.2 | S25: A1110.8 | T25: A1110.3 | U25: A1110.4 | V25: A1110.5 | W25: A1110.6 | X25: A1110.7
A26: FLUO ABS | B26: A1111 | C26: =VLOOKUP(Q26,Data!$B:$E,4,FALSE) -> #N/A | D26: =VLOOKUP(R26,Data!$B:$E,4,FALSE) -> #N/A | E26: =VLOOKUP(S26,Data!$B:$E,4,FALSE) -> #N/A | F26: =VLOOKUP(T26,Data!$B:$E,4,FALSE) -> #N/A | G26: =VLOOKUP(U26,Data!$B:$E,4,FALSE) -> #N/A | H26: =VLOOKUP(V26,Data!$B:$E,4,FALSE) -> #N/A | I26: =VLOOKUP(W26,Data!$B:$E,4,FALSE) -> #N/A | J26: =VLOOKUP(X26,Data!$B:$E,4,FALSE) -> #N/A | O26: FLUO ABS | P26: A1111 | Q26: A1111.1 | R26: A1111.2 | S26: A1111.8 | T26: A1111.3 | U26: A1111.4 | V26: A1111.5 | W26: A1111.6 | X26: A1111.7
A27: =Translation!A55 -> TOTAL DE VENDAS - LINHA 125 cc | B27: A1120 | C27: =VLOOKUP(Q27,Data!$B:$E,4,FALSE) -> #N/A | D27: =VLOOKUP(R27,Data!$B:$E,4,FALSE) -> #N/A | E27: =VLOOKUP(S27,Data!$B:$E,4,FALSE) -> #N/A | F27: =VLOOKUP(T27,Data!$B:$E,4,FALSE) -> #N/A | G27: =VLOOKUP(U27,Data!$B:$E,4,FALSE) -> #N/A | H27: =VLOOKUP(V27,Data!$B:$E,4,FALSE) -> #N/A | I27: =VLOOKUP(W27,Data!$B:$E,4,FALSE) -> #N/A | J27: =VLOOKUP(X27,Data!$B:$E,4,FALSE) -> #N/A | O27: TOTAL DE VENDAS - LINHA 125 cc | P27: A1120 | Q27: A1120.1 | R27: A1120.2 | S27: A1120.8 | T27: A1120.3 | U27: A1120.4 | V27: A1120.5 | W27: A1120.6 | X27: A1120.7
A28: =Translation!A56 -> LINHA 150 cc - Street | B28: =Translation!$G$32 -> CONTA | C28: =Translation!$G$12 -> UNIDADES | D28: =Translation!$G$11 -> RECEITA (SEM IMPOSTOS) | E28: =Translation!$G$33 -> UNIDADES DEVOLVIDAS | F28: =Translation!$G$14 -> DEVOLUÇÃO DE VENDAS | G28: =Translation!$G$3 -> ABAT. E DESCONTO | H28: =Translation!$G$9 -> RECEITA LÍQUIDA | I28: =Translation!$G$2 -> CUSTO | J28: =Translation!$G$5 -> LUCRO BRUTO | O28: LINHA 150 cc - Street | P28: =Translation!$G$32 -> CONTA | Q28: UNITS | R28: SALES | S28: URETURN | T28: SC | U28: DISC | V28: NS | W28: COS | X28: GP
A29: =Translation!A57 -> FACTOR 150E | B29: A1130 | C29: =VLOOKUP(Q29,Data!$B:$E,4,FALSE) -> #N/A | D29: =VLOOKUP(R29,Data!$B:$E,4,FALSE) -> #N/A | E29: =VLOOKUP(S29,Data!$B:$E,4,FALSE) -> #N/A | F29: =VLOOKUP(T29,Data!$B:$E,4,FALSE) -> #N/A | G29: =VLOOKUP(U29,Data!$B:$E,4,FALSE) -> #N/A | H29: =VLOOKUP(V29,Data!$B:$E,4,FALSE) -> #N/A | I29: =VLOOKUP(W29,Data!$B:$E,4,FALSE) -> #N/A | J29: =VLOOKUP(X29,Data!$B:$E,4,FALSE) -> #N/A | O29: FACTOR 150E | P29: A1130 | Q29: A1130.1 | R29: A1130.2 | S29: A1130.8 | T29: A1130.3 | U29: A1130.4 | V29: A1130.5 | W29: A1130.6 | X29: A1130.7
A30: =Translation!A58 -> FACTOR 150ED | B30: A1140 | C30: =VLOOKUP(Q30,Data!$B:$E,4,FALSE) -> #N/A | D30: =VLOOKUP(R30,Data!$B:$E,4,FALSE) -> #N/A | E30: =VLOOKUP(S30,Data!$B:$E,4,FALSE) -> #N/A | F30: =VLOOKUP(T30,Data!$B:$E,4,FALSE) -> #N/A | G30: =VLOOKUP(U30,Data!$B:$E,4,FALSE) -> #N/A | H30: =VLOOKUP(V30,Data!$B:$E,4,FALSE) -> #N/A | I30: =VLOOKUP(W30,Data!$B:$E,4,FALSE) -> #N/A | J30: =VLOOKUP(X30,Data!$B:$E,4,FALSE) -> #N/A | O30: FACTOR 150ED | P30: A1140 | Q30: A1140.1 | R30: A1140.2 | S30: A1140.8 | T30: A1140.3 | U30: A1140.4 | V30: A1140.5 | W30: A1140.6 | X30: A1140.7
A31: =Translation!A59 -> YS 150 FAZER SED | B31: A1150 | C31: =VLOOKUP(Q31,Data!$B:$E,4,FALSE) -> #N/A | D31: =VLOOKUP(R31,Data!$B:$E,4,FALSE) -> #N/A | E31: =VLOOKUP(S31,Data!$B:$E,4,FALSE) -> #N/A | F31: =VLOOKUP(T31,Data!$B:$E,4,FALSE) -> #N/A | G31: =VLOOKUP(U31,Data!$B:$E,4,FALSE) -> #N/A | H31: =VLOOKUP(V31,Data!$B:$E,4,FALSE) -> #N/A | I31: =VLOOKUP(W31,Data!$B:$E,4,FALSE) -> #N/A | J31: =VLOOKUP(X31,Data!$B:$E,4,FALSE) -> #N/A | O31: YS 150 FAZER SED | P31: A1150 | Q31: A1150.1 | R31: A1150.2 | S31: A1150.8 | T31: A1150.3 | U31: A1150.4 | V31: A1150.5 | W31: A1150.6 | X31: A1150.7
A32: YZF R15 ABS | B32: A1151 | C32: =VLOOKUP(Q32,Data!$B:$E,4,FALSE) -> #N/A | D32: =VLOOKUP(R32,Data!$B:$E,4,FALSE) -> #N/A | E32: =VLOOKUP(S32,Data!$B:$E,4,FALSE) -> #N/A | F32: =VLOOKUP(T32,Data!$B:$E,4,FALSE) -> #N/A | G32: =VLOOKUP(U32,Data!$B:$E,4,FALSE) -> #N/A | H32: =VLOOKUP(V32,Data!$B:$E,4,FALSE) -> #N/A | I32: =VLOOKUP(W32,Data!$B:$E,4,FALSE) -> #N/A | J32: =VLOOKUP(X32,Data!$B:$E,4,FALSE) -> #N/A | O32: YZF R15 ABS | P32: A1151 | Q32: A1151.1 | R32: A1151.2 | S32: A1151.8 | T32: A1151.3 | U32: A1151.4 | V32: A1151.5 | W32: A1151.6 | X32: A1151.7
A33: FZ15 FAZER ABS | B33: A1152 | C33: =VLOOKUP(Q33,Data!$B:$E,4,FALSE) -> #N/A | D33: =VLOOKUP(R33,Data!$B:$E,4,FALSE) -> #N/A | E33: =VLOOKUP(S33,Data!$B:$E,4,FALSE) -> #N/A | F33: =VLOOKUP(T33,Data!$B:$E,4,FALSE) -> #N/A | G33: =VLOOKUP(U33,Data!$B:$E,4,FALSE) -> #N/A | H33: =VLOOKUP(V33,Data!$B:$E,4,FALSE) -> #N/A | I33: =VLOOKUP(W33,Data!$B:$E,4,FALSE) -> #N/A | J33: =VLOOKUP(X33,Data!$B:$E,4,FALSE) -> #N/A | O33: FZ15 FAZER ABS | P33: A1152 | Q33: A1152.1 | R33: A1152.2 | S33: A1152.8 | T33: A1152.3 | U33: A1152.4 | V33: A1152.5 | W33: A1152.6 | X33: A1152.7
A34: =Translation!A60 -> LINHA 150 cc - On/Off | B34: =Translation!$G$32 -> CONTA | C34: =Translation!$G$12 -> UNIDADES | D34: =Translation!$G$11 -> RECEITA (SEM IMPOSTOS) | E34: =Translation!$G$33 -> UNIDADES DEVOLVIDAS | F34: =Translation!$G$14 -> DEVOLUÇÃO DE VENDAS | G34: =Translation!$G$3 -> ABAT. E DESCONTO | H34: =Translation!$G$9 -> RECEITA LÍQUIDA | I34: =Translation!$G$2 -> CUSTO | J34: =Translation!$G$5 -> LUCRO BRUTO | O34: LINHA 150 cc - On/Off | P34: =Translation!$G$32 -> CONTA | Q34: UNITS | R34: SALES | S34: URETURN | T34: SC | U34: DISC | V34: NS | W34: COS | X34: GP
A35: =Translation!A61 -> XTZ 150 CROSSER E | B35: A1160 | C35: =VLOOKUP(Q35,Data!$B:$E,4,FALSE) -> #N/A | D35: =VLOOKUP(R35,Data!$B:$E,4,FALSE) -> #N/A | E35: =VLOOKUP(S35,Data!$B:$E,4,FALSE) -> #N/A | F35: =VLOOKUP(T35,Data!$B:$E,4,FALSE) -> #N/A | G35: =VLOOKUP(U35,Data!$B:$E,4,FALSE) -> #N/A | H35: =VLOOKUP(V35,Data!$B:$E,4,FALSE) -> #N/A | I35: =VLOOKUP(W35,Data!$B:$E,4,FALSE) -> #N/A | J35: =VLOOKUP(X35,Data!$B:$E,4,FALSE) -> #N/A | O35: XTZ 150 CROSSER E | P35: A1160 | Q35: A1160.1 | R35: A1160.2 | S35: A1160.8 | T35: A1160.3 | U35: A1160.4 | V35: A1160.5 | W35: A1160.6 | X35: A1160.7
A36: =Translation!A62 -> XTZ 150 CROSSER ED | B36: A1170 | C36: =VLOOKUP(Q36,Data!$B:$E,4,FALSE) -> #N/A | D36: =VLOOKUP(R36,Data!$B:$E,4,FALSE) -> #N/A | E36: =VLOOKUP(S36,Data!$B:$E,4,FALSE) -> #N/A | F36: =VLOOKUP(T36,Data!$B:$E,4,FALSE) -> #N/A | G36: =VLOOKUP(U36,Data!$B:$E,4,FALSE) -> #N/A | H36: =VLOOKUP(V36,Data!$B:$E,4,FALSE) -> #N/A | I36: =VLOOKUP(W36,Data!$B:$E,4,FALSE) -> #N/A | J36: =VLOOKUP(X36,Data!$B:$E,4,FALSE) -> #N/A | O36: XTZ 150 CROSSER ED | P36: A1170 | Q36: A1170.1 | R36: A1170.2 | S36: A1170.8 | T36: A1170.3 | U36: A1170.4 | V36: A1170.5 | W36: A1170.6 | X36: A1170.7
A37: XTZ 150 CROSSER S | B37: A1174 | C37: =VLOOKUP(Q37,Data!$B:$E,4,FALSE) -> #N/A | D37: =VLOOKUP(R37,Data!$B:$E,4,FALSE) -> #N/A | E37: =VLOOKUP(S37,Data!$B:$E,4,FALSE) -> #N/A | F37: =VLOOKUP(T37,Data!$B:$E,4,FALSE) -> #N/A | G37: =VLOOKUP(U37,Data!$B:$E,4,FALSE) -> #N/A | H37: =VLOOKUP(V37,Data!$B:$E,4,FALSE) -> #N/A | I37: =VLOOKUP(W37,Data!$B:$E,4,FALSE) -> #N/A | J37: =VLOOKUP(X37,Data!$B:$E,4,FALSE) -> #N/A | O37: XTZ 150 CROSSER S | P37: A1174 | Q37: A1174.1 | R37: A1174.2 | S37: A1174.8 | T37: A1174.3 | U37: A1174.4 | V37: A1174.5 | W37: A1174.6 | X37: A1174.7
A38: XTZ 150 CROSSER Z | B38: A1176 | C38: =VLOOKUP(Q38,Data!$B:$E,4,FALSE) -> #N/A | D38: =VLOOKUP(R38,Data!$B:$E,4,FALSE) -> #N/A | E38: =VLOOKUP(S38,Data!$B:$E,4,FALSE) -> #N/A | F38: =VLOOKUP(T38,Data!$B:$E,4,FALSE) -> #N/A | G38: =VLOOKUP(U38,Data!$B:$E,4,FALSE) -> #N/A | H38: =VLOOKUP(V38,Data!$B:$E,4,FALSE) -> #N/A | I38: =VLOOKUP(W38,Data!$B:$E,4,FALSE) -> #N/A | J38: =VLOOKUP(X38,Data!$B:$E,4,FALSE) -> #N/A | O38: XTZ 150 CROSSER Z | P38: A1176 | Q38: A1176.1 | R38: A1176.2 | S38: A1176.8 | T38: A1176.3 | U38: A1176.4 | V38: A1176.5 | W38: A1176.6 | X38: A1176.7
A39: =Translation!A63 -> TOTAL DE VENDAS - LINHA 150 cc | B39: A1180 | C39: =VLOOKUP(Q39,Data!$B:$E,4,FALSE) -> #N/A | D39: =VLOOKUP(R39,Data!$B:$E,4,FALSE) -> #N/A | E39: =VLOOKUP(S39,Data!$B:$E,4,FALSE) -> #N/A | F39: =VLOOKUP(T39,Data!$B:$E,4,FALSE) -> #N/A | G39: =VLOOKUP(U39,Data!$B:$E,4,FALSE) -> #N/A | H39: =VLOOKUP(V39,Data!$B:$E,4,FALSE) -> #N/A | I39: =VLOOKUP(W39,Data!$B:$E,4,FALSE) -> #N/A | J39: =VLOOKUP(X39,Data!$B:$E,4,FALSE) -> #N/A | O39: TOTAL DE VENDAS - LINHA 150 cc | P39: A1180 | Q39: A1180.1 | R39: A1180.2 | S39: A1180.8 | T39: A1180.3 | U39: A1180.4 | V39: A1180.5 | W39: A1180.6 | X39: A1180.7
A40: =Translation!A64 -> LINHA 250 cc - Street | B40: =Translation!$G$32 -> CONTA | C40: =Translation!$G$12 -> UNIDADES | D40: =Translation!$G$11 -> RECEITA (SEM IMPOSTOS) | E40: =Translation!$G$33 -> UNIDADES DEVOLVIDAS | F40: =Translation!$G$14 -> DEVOLUÇÃO DE VENDAS | G40: =Translation!$G$3 -> ABAT. E DESCONTO | H40: =Translation!$G$9 -> RECEITA LÍQUIDA | I40: =Translation!$G$2 -> CUSTO | J40: =Translation!$G$5 -> LUCRO BRUTO | O40: LINHA 250 cc - Street | P40: =Translation!$G$32 -> CONTA | Q40: UNITS | R40: SALES | S40: URETURN | T40: SC | U40: DISC | V40: NS | W40: COS | X40: GP
A41: =Translation!A65 -> YS 250 FAZER BLUEFLEX | B41: A1190 | C41: =VLOOKUP(Q41,Data!$B:$E,4,FALSE) -> #N/A | D41: =VLOOKUP(R41,Data!$B:$E,4,FALSE) -> #N/A | E41: =VLOOKUP(S41,Data!$B:$E,4,FALSE) -> #N/A | F41: =VLOOKUP(T41,Data!$B:$E,4,FALSE) -> #N/A | G41: =VLOOKUP(U41,Data!$B:$E,4,FALSE) -> #N/A | H41: =VLOOKUP(V41,Data!$B:$E,4,FALSE) -> #N/A | I41: =VLOOKUP(W41,Data!$B:$E,4,FALSE) -> #N/A | J41: =VLOOKUP(X41,Data!$B:$E,4,FALSE) -> #N/A | O41: YS 250 FAZER BLUEFLEX | P41: A1190 | Q41: A1190.1 | R41: A1190.2 | S41: A1190.8 | T41: A1190.3 | U41: A1190.4 | V41: A1190.5 | W41: A1190.6 | X41: A1190.7
A42: FZ25 FAZER ABS | B42: A1195 | C42: =VLOOKUP(Q42,Data!$B:$E,4,FALSE) -> #N/A | D42: =VLOOKUP(R42,Data!$B:$E,4,FALSE) -> #N/A | E42: =VLOOKUP(S42,Data!$B:$E,4,FALSE) -> #N/A | F42: =VLOOKUP(T42,Data!$B:$E,4,FALSE) -> #N/A | G42: =VLOOKUP(U42,Data!$B:$E,4,FALSE) -> #N/A | H42: =VLOOKUP(V42,Data!$B:$E,4,FALSE) -> #N/A | I42: =VLOOKUP(W42,Data!$B:$E,4,FALSE) -> #N/A | J42: =VLOOKUP(X42,Data!$B:$E,4,FALSE) -> #N/A | O42: FZ25 FAZER ABS | P42: A1195 | Q42: A1195.1 | R42: A1195.2 | S42: A1195.8 | T42: A1195.3 | U42: A1195.4 | V42: A1195.5 | W42: A1195.6 | X42: A1195.7
A43: =Translation!A66 -> LINHA 250 cc - On/Off | B43: =Translation!$G$32 -> CONTA | C43: =Translation!$G$12 -> UNIDADES | D43: =Translation!$G$11 -> RECEITA (SEM IMPOSTOS) | E43: =Translation!$G$33 -> UNIDADES DEVOLVIDAS | F43: =Translation!$G$14 -> DEVOLUÇÃO DE VENDAS | G43: =Translation!$G$3 -> ABAT. E DESCONTO | H43: =Translation!$G$9 -> RECEITA LÍQUIDA | I43: =Translation!$G$2 -> CUSTO | J43: =Translation!$G$5 -> LUCRO BRUTO | O43: LINHA 250 cc - On/Off | P43: =Translation!$G$32 -> CONTA | Q43: UNITS | R43: SALES | S43: URETURN | T43: SC | U43: DISC | V43: NS | W43: COS | X43: GP
A44: =Translation!A67 -> XTZ 250 LANDER | B44: A1200 | C44: =VLOOKUP(Q44,Data!$B:$E,4,FALSE) -> #N/A | D44: =VLOOKUP(R44,Data!$B:$E,4,FALSE) -> #N/A | E44: =VLOOKUP(S44,Data!$B:$E,4,FALSE) -> #N/A | F44: =VLOOKUP(T44,Data!$B:$E,4,FALSE) -> #N/A | G44: =VLOOKUP(U44,Data!$B:$E,4,FALSE) -> #N/A | H44: =VLOOKUP(V44,Data!$B:$E,4,FALSE) -> #N/A | I44: =VLOOKUP(W44,Data!$B:$E,4,FALSE) -> #N/A | J44: =VLOOKUP(X44,Data!$B:$E,4,FALSE) -> #N/A | O44: XTZ 250 LANDER | P44: A1200 | Q44: A1200.1 | R44: A1200.2 | S44: A1200.8 | T44: A1200.3 | U44: A1200.4 | V44: A1200.5 | W44: A1200.6 | X44: A1200.7
A45: =Translation!A68 -> XTZ 250 TENERE | B45: A1210 | C45: =VLOOKUP(Q45,Data!$B:$E,4,FALSE) -> #N/A | D45: =VLOOKUP(R45,Data!$B:$E,4,FALSE) -> #N/A | E45: =VLOOKUP(S45,Data!$B:$E,4,FALSE) -> #N/A | F45: =VLOOKUP(T45,Data!$B:$E,4,FALSE) -> #N/A | G45: =VLOOKUP(U45,Data!$B:$E,4,FALSE) -> #N/A | H45: =VLOOKUP(V45,Data!$B:$E,4,FALSE) -> #N/A | I45: =VLOOKUP(W45,Data!$B:$E,4,FALSE) -> #N/A | J45: =VLOOKUP(X45,Data!$B:$E,4,FALSE) -> #N/A | O45: XTZ 250 TENERE | P45: A1210 | Q45: A1210.1 | R45: A1210.2 | S45: A1210.8 | T45: A1210.3 | U45: A1210.4 | V45: A1210.5 | W45: A1210.6 | X45: A1210.7
A46: =Translation!A69 -> TOTAL DE VENDAS - LINHA 250 cc | B46: A1220 | C46: =VLOOKUP(Q46,Data!$B:$E,4,FALSE) -> #N/A | D46: =VLOOKUP(R46,Data!$B:$E,4,FALSE) -> #N/A | E46: =VLOOKUP(S46,Data!$B:$E,4,FALSE) -> #N/A | F46: =VLOOKUP(T46,Data!$B:$E,4,FALSE) -> #N/A | G46: =VLOOKUP(U46,Data!$B:$E,4,FALSE) -> #N/A | H46: =VLOOKUP(V46,Data!$B:$E,4,FALSE) -> #N/A | I46: =VLOOKUP(W46,Data!$B:$E,4,FALSE) -> #N/A | J46: =VLOOKUP(X46,Data!$B:$E,4,FALSE) -> #N/A | O46: TOTAL DE VENDAS - LINHA 250 cc | P46: A1220 | Q46: A1220.1 | R46: A1220.2 | S46: A1220.8 | T46: A1220.3 | U46: A1220.4 | V46: A1220.5 | W46: A1220.6 | X46: A1220.7
A47: =Translation!A70 -> LINHA 320 cc | B47: =Translation!$G$32 -> CONTA | C47: =Translation!$G$12 -> UNIDADES | D47: =Translation!$G$11 -> RECEITA (SEM IMPOSTOS) | E47: =Translation!$G$33 -> UNIDADES DEVOLVIDAS | F47: =Translation!$G$14 -> DEVOLUÇÃO DE VENDAS | G47: =Translation!$G$3 -> ABAT. E DESCONTO | H47: =Translation!$G$9 -> RECEITA LÍQUIDA | I47: =Translation!$G$2 -> CUSTO | J47: =Translation!$G$5 -> LUCRO BRUTO | O47: LINHA 320 cc | P47: =Translation!$G$32 -> CONTA | Q47: UNITS | R47: SALES | S47: URETURN | T47: SC | U47: DISC | V47: NS | W47: COS | X47: GP
A48: =Translation!A71 -> YZF R3 | B48: A1230 | C48: =VLOOKUP(Q48,Data!$B:$E,4,FALSE) -> #N/A | D48: =VLOOKUP(R48,Data!$B:$E,4,FALSE) -> #N/A | E48: =VLOOKUP(S48,Data!$B:$E,4,FALSE) -> #N/A | F48: =VLOOKUP(T48,Data!$B:$E,4,FALSE) -> #N/A | G48: =VLOOKUP(U48,Data!$B:$E,4,FALSE) -> #N/A | H48: =VLOOKUP(V48,Data!$B:$E,4,FALSE) -> #N/A | I48: =VLOOKUP(W48,Data!$B:$E,4,FALSE) -> #N/A | J48: =VLOOKUP(X48,Data!$B:$E,4,FALSE) -> #N/A | O48: YZF R3 | P48: A1230 | Q48: A1230.1 | R48: A1230.2 | S48: A1230.8 | T48: A1230.3 | U48: A1230.4 | V48: A1230.5 | W48: A1230.6 | X48: A1230.7
A49: =Translation!A72 -> YZF R3 ABS | B49: A1240 | C49: =VLOOKUP(Q49,Data!$B:$E,4,FALSE) -> #N/A | D49: =VLOOKUP(R49,Data!$B:$E,4,FALSE) -> #N/A | E49: =VLOOKUP(S49,Data!$B:$E,4,FALSE) -> #N/A | F49: =VLOOKUP(T49,Data!$B:$E,4,FALSE) -> #N/A | G49: =VLOOKUP(U49,Data!$B:$E,4,FALSE) -> #N/A | H49: =VLOOKUP(V49,Data!$B:$E,4,FALSE) -> #N/A | I49: =VLOOKUP(W49,Data!$B:$E,4,FALSE) -> #N/A | J49: =VLOOKUP(X49,Data!$B:$E,4,FALSE) -> #N/A | O49: YZF R3 ABS | P49: A1240 | Q49: A1240.1 | R49: A1240.2 | S49: A1240.8 | T49: A1240.3 | U49: A1240.4 | V49: A1240.5 | W49: A1240.6 | X49: A1240.7
A50: =Translation!A73 -> MT03 | B50: A1250 | C50: =VLOOKUP(Q50,Data!$B:$E,4,FALSE) -> #N/A | D50: =VLOOKUP(R50,Data!$B:$E,4,FALSE) -> #N/A | E50: =VLOOKUP(S50,Data!$B:$E,4,FALSE) -> #N/A | F50: =VLOOKUP(T50,Data!$B:$E,4,FALSE) -> #N/A | G50: =VLOOKUP(U50,Data!$B:$E,4,FALSE) -> #N/A | H50: =VLOOKUP(V50,Data!$B:$E,4,FALSE) -> #N/A | I50: =VLOOKUP(W50,Data!$B:$E,4,FALSE) -> #N/A | J50: =VLOOKUP(X50,Data!$B:$E,4,FALSE) -> #N/A | O50: MT03 | P50: A1250 | Q50: A1250.1 | R50: A1250.2 | S50: A1250.8 | T50: A1250.3 | U50: A1250.4 | V50: A1250.5 | W50: A1250.6 | X50: A1250.7
A51: =Translation!A74 -> MT03 ABS | B51: A1260 | C51: =VLOOKUP(Q51,Data!$B:$E,4,FALSE) -> #N/A | D51: =VLOOKUP(R51,Data!$B:$E,4,FALSE) -> #N/A | E51: =VLOOKUP(S51,Data!$B:$E,4,FALSE) -> #N/A | F51: =VLOOKUP(T51,Data!$B:$E,4,FALSE) -> #N/A | G51: =VLOOKUP(U51,Data!$B:$E,4,FALSE) -> #N/A | H51: =VLOOKUP(V51,Data!$B:$E,4,FALSE) -> #N/A | I51: =VLOOKUP(W51,Data!$B:$E,4,FALSE) -> #N/A | J51: =VLOOKUP(X51,Data!$B:$E,4,FALSE) -> #N/A | O51: MT03 ABS | P51: A1260 | Q51: A1260.1 | R51: A1260.2 | S51: A1260.8 | T51: A1260.3 | U51: A1260.4 | V51: A1260.5 | W51: A1260.6 | X51: A1260.7
A52: =Translation!A75 -> TOTAL DE VENDAS - LINHA 320 cc | B52: A1270 | C52: =VLOOKUP(Q52,Data!$B:$E,4,FALSE) -> #N/A | D52: =VLOOKUP(R52,Data!$B:$E,4,FALSE) -> #N/A | E52: =VLOOKUP(S52,Data!$B:$E,4,FALSE) -> #N/A | F52: =VLOOKUP(T52,Data!$B:$E,4,FALSE) -> #N/A | G52: =VLOOKUP(U52,Data!$B:$E,4,FALSE) -> #N/A | H52: =VLOOKUP(V52,Data!$B:$E,4,FALSE) -> #N/A | I52: =VLOOKUP(W52,Data!$B:$E,4,FALSE) -> #N/A | J52: =VLOOKUP(X52,Data!$B:$E,4,FALSE) -> #N/A | O52: TOTAL DE VENDAS - LINHA 320 cc | P52: A1270 | Q52: A1270.1 | R52: A1270.2 | S52: A1270.8 | T52: A1270.3 | U52: A1270.4 | V52: A1270.5 | W52: A1270.6 | X52: A1270.7
A53: =Translation!A76 -> LINHA > 500 cc | B53: =Translation!$G$32 -> CONTA | C53: =Translation!$G$12 -> UNIDADES | D53: =Translation!$G$11 -> RECEITA (SEM IMPOSTOS) | E53: =Translation!$G$33 -> UNIDADES DEVOLVIDAS | F53: =Translation!$G$14 -> DEVOLUÇÃO DE VENDAS | G53: =Translation!$G$3 -> ABAT. E DESCONTO | H53: =Translation!$G$9 -> RECEITA LÍQUIDA | I53: =Translation!$G$2 -> CUSTO | J53: =Translation!$G$5 -> LUCRO BRUTO | O53: LINHA > 500 cc | P53: =Translation!$G$32 -> CONTA | Q53: UNITS | R53: SALES | S53: URETURN | T53: SC | U53: DISC | V53: NS | W53: COS | X53: GP
A54: =Translation!A77 -> XJ6 N ABS | B54: A1280 | C54: =VLOOKUP(Q54,Data!$B:$E,4,FALSE) -> #N/A | D54: =VLOOKUP(R54,Data!$B:$E,4,FALSE) -> #N/A | E54: =VLOOKUP(S54,Data!$B:$E,4,FALSE) -> #N/A | F54: =VLOOKUP(T54,Data!$B:$E,4,FALSE) -> #N/A | G54: =VLOOKUP(U54,Data!$B:$E,4,FALSE) -> #N/A | H54: =VLOOKUP(V54,Data!$B:$E,4,FALSE) -> #N/A | I54: =VLOOKUP(W54,Data!$B:$E,4,FALSE) -> #N/A | J54: =VLOOKUP(X54,Data!$B:$E,4,FALSE) -> #N/A | O54: XJ6 N ABS | P54: A1280 | Q54: A1280.1 | R54: A1280.2 | S54: A1280.8 | T54: A1280.3 | U54: A1280.4 | V54: A1280.5 | W54: A1280.6 | X54: A1280.7
A55: =Translation!A78 -> XJ6 F ABS | B55: A1290 | C55: =VLOOKUP(Q55,Data!$B:$E,4,FALSE) -> #N/A | D55: =VLOOKUP(R55,Data!$B:$E,4,FALSE) -> #N/A | E55: =VLOOKUP(S55,Data!$B:$E,4,FALSE) -> #N/A | F55: =VLOOKUP(T55,Data!$B:$E,4,FALSE) -> #N/A | G55: =VLOOKUP(U55,Data!$B:$E,4,FALSE) -> #N/A | H55: =VLOOKUP(V55,Data!$B:$E,4,FALSE) -> #N/A | I55: =VLOOKUP(W55,Data!$B:$E,4,FALSE) -> #N/A | J55: =VLOOKUP(X55,Data!$B:$E,4,FALSE) -> #N/A | O55: XJ6 F ABS | P55: A1290 | Q55: A1290.1 | R55: A1290.2 | S55: A1290.8 | T55: A1290.3 | U55: A1290.4 | V55: A1290.5 | W55: A1290.6 | X55: A1290.7
A56: =Translation!A79 -> XT 660R | B56: A1300 | C56: =VLOOKUP(Q56,Data!$B:$E,4,FALSE) -> #N/A | D56: =VLOOKUP(R56,Data!$B:$E,4,FALSE) -> #N/A | E56: =VLOOKUP(S56,Data!$B:$E,4,FALSE) -> #N/A | F56: =VLOOKUP(T56,Data!$B:$E,4,FALSE) -> #N/A | G56: =VLOOKUP(U56,Data!$B:$E,4,FALSE) -> #N/A | H56: =VLOOKUP(V56,Data!$B:$E,4,FALSE) -> #N/A | I56: =VLOOKUP(W56,Data!$B:$E,4,FALSE) -> #N/A | J56: =VLOOKUP(X56,Data!$B:$E,4,FALSE) -> #N/A | O56: XT 660R | P56: A1300 | Q56: A1300.1 | R56: A1300.2 | S56: A1300.8 | T56: A1300.3 | U56: A1300.4 | V56: A1300.5 | W56: A1300.6 | X56: A1300.7
A57: =Translation!A80 -> XT 660Z TENERE ABS | B57: A1310 | C57: =VLOOKUP(Q57,Data!$B:$E,4,FALSE) -> #N/A | D57: =VLOOKUP(R57,Data!$B:$E,4,FALSE) -> #N/A | E57: =VLOOKUP(S57,Data!$B:$E,4,FALSE) -> #N/A | F57: =VLOOKUP(T57,Data!$B:$E,4,FALSE) -> #N/A | G57: =VLOOKUP(U57,Data!$B:$E,4,FALSE) -> #N/A | H57: =VLOOKUP(V57,Data!$B:$E,4,FALSE) -> #N/A | I57: =VLOOKUP(W57,Data!$B:$E,4,FALSE) -> #N/A | J57: =VLOOKUP(X57,Data!$B:$E,4,FALSE) -> #N/A | O57: XT 660Z TENERE ABS | P57: A1310 | Q57: A1310.1 | R57: A1310.2 | S57: A1310.8 | T57: A1310.3 | U57: A1310.4 | V57: A1310.5 | W57: A1310.6 | X57: A1310.7
A58: =Translation!A81 -> MT07 | B58: A1320 | C58: =VLOOKUP(Q58,Data!$B:$E,4,FALSE) -> #N/A | D58: =VLOOKUP(R58,Data!$B:$E,4,FALSE) -> #N/A | E58: =VLOOKUP(S58,Data!$B:$E,4,FALSE) -> #N/A | F58: =VLOOKUP(T58,Data!$B:$E,4,FALSE) -> #N/A | G58: =VLOOKUP(U58,Data!$B:$E,4,FALSE) -> #N/A | H58: =VLOOKUP(V58,Data!$B:$E,4,FALSE) -> #N/A | I58: =VLOOKUP(W58,Data!$B:$E,4,FALSE) -> #N/A | J58: =VLOOKUP(X58,Data!$B:$E,4,FALSE) -> #N/A | O58: MT07 | P58: A1320 | Q58: A1320.1 | R58: A1320.2 | S58: A1320.8 | T58: A1320.3 | U58: A1320.4 | V58: A1320.5 | W58: A1320.6 | X58: A1320.7
A59: =Translation!A82 -> MT07 ABS | B59: A1330 | C59: =VLOOKUP(Q59,Data!$B:$E,4,FALSE) -> #N/A | D59: =VLOOKUP(R59,Data!$B:$E,4,FALSE) -> #N/A | E59: =VLOOKUP(S59,Data!$B:$E,4,FALSE) -> #N/A | F59: =VLOOKUP(T59,Data!$B:$E,4,FALSE) -> #N/A | G59: =VLOOKUP(U59,Data!$B:$E,4,FALSE) -> #N/A | H59: =VLOOKUP(V59,Data!$B:$E,4,FALSE) -> #N/A | I59: =VLOOKUP(W59,Data!$B:$E,4,FALSE) -> #N/A | J59: =VLOOKUP(X59,Data!$B:$E,4,FALSE) -> #N/A | O59: MT07 ABS | P59: A1330 | Q59: A1330.1 | R59: A1330.2 | S59: A1330.8 | T59: A1330.3 | U59: A1330.4 | V59: A1330.5 | W59: A1330.6 | X59: A1330.7
A60: =Translation!A83 -> MT09 | B60: A1340 | C60: =VLOOKUP(Q60,Data!$B:$E,4,FALSE) -> #N/A | D60: =VLOOKUP(R60,Data!$B:$E,4,FALSE) -> #N/A | E60: =VLOOKUP(S60,Data!$B:$E,4,FALSE) -> #N/A | F60: =VLOOKUP(T60,Data!$B:$E,4,FALSE) -> #N/A | G60: =VLOOKUP(U60,Data!$B:$E,4,FALSE) -> #N/A | H60: =VLOOKUP(V60,Data!$B:$E,4,FALSE) -> #N/A | I60: =VLOOKUP(W60,Data!$B:$E,4,FALSE) -> #N/A | J60: =VLOOKUP(X60,Data!$B:$E,4,FALSE) -> #N/A | O60: MT09 | P60: A1340 | Q60: A1340.1 | R60: A1340.2 | S60: A1340.8 | T60: A1340.3 | U60: A1340.4 | V60: A1340.5 | W60: A1340.6 | X60: A1340.7
A61: =Translation!A84 -> MT09 SP | B61: A1350 | C61: =VLOOKUP(Q61,Data!$B:$E,4,FALSE) -> #N/A | D61: =VLOOKUP(R61,Data!$B:$E,4,FALSE) -> #N/A | E61: =VLOOKUP(S61,Data!$B:$E,4,FALSE) -> #N/A | F61: =VLOOKUP(T61,Data!$B:$E,4,FALSE) -> #N/A | G61: =VLOOKUP(U61,Data!$B:$E,4,FALSE) -> #N/A | H61: =VLOOKUP(V61,Data!$B:$E,4,FALSE) -> #N/A | I61: =VLOOKUP(W61,Data!$B:$E,4,FALSE) -> #N/A | J61: =VLOOKUP(X61,Data!$B:$E,4,FALSE) -> #N/A | O61: MT09 SP | P61: A1350 | Q61: A1350.1 | R61: A1350.2 | S61: A1350.8 | T61: A1350.3 | U61: A1350.4 | V61: A1350.5 | W61: A1350.6 | X61: A1350.7
A62: =Translation!A85 -> MT09 TRACER | B62: A1360 | C62: =VLOOKUP(Q62,Data!$B:$E,4,FALSE) -> #N/A | D62: =VLOOKUP(R62,Data!$B:$E,4,FALSE) -> #N/A | E62: =VLOOKUP(S62,Data!$B:$E,4,FALSE) -> #N/A | F62: =VLOOKUP(T62,Data!$B:$E,4,FALSE) -> #N/A | G62: =VLOOKUP(U62,Data!$B:$E,4,FALSE) -> #N/A | H62: =VLOOKUP(V62,Data!$B:$E,4,FALSE) -> #N/A | I62: =VLOOKUP(W62,Data!$B:$E,4,FALSE) -> #N/A | J62: =VLOOKUP(X62,Data!$B:$E,4,FALSE) -> #N/A | O62: MT09 TRACER | P62: A1360 | Q62: A1360.1 | R62: A1360.2 | S62: A1360.8 | T62: A1360.3 | U62: A1360.4 | V62: A1360.5 | W62: A1360.6 | X62: A1360.7
A63: =Translation!A86 -> YZF R1 | B63: A1370 | C63: =VLOOKUP(Q63,Data!$B:$E,4,FALSE) -> #N/A | D63: =VLOOKUP(R63,Data!$B:$E,4,FALSE) -> #N/A | E63: =VLOOKUP(S63,Data!$B:$E,4,FALSE) -> #N/A | F63: =VLOOKUP(T63,Data!$B:$E,4,FALSE) -> #N/A | G63: =VLOOKUP(U63,Data!$B:$E,4,FALSE) -> #N/A | H63: =VLOOKUP(V63,Data!$B:$E,4,FALSE) -> #N/A | I63: =VLOOKUP(W63,Data!$B:$E,4,FALSE) -> #N/A | J63: =VLOOKUP(X63,Data!$B:$E,4,FALSE) -> #N/A | O63: YZF R1 | P63: A1370 | Q63: A1370.1 | R63: A1370.2 | S63: A1370.8 | T63: A1370.3 | U63: A1370.4 | V63: A1370.5 | W63: A1370.6 | X63: A1370.7
A64: =Translation!A87 -> YZF R1M | B64: A1380 | C64: =VLOOKUP(Q64,Data!$B:$E,4,FALSE) -> #N/A | D64: =VLOOKUP(R64,Data!$B:$E,4,FALSE) -> #N/A | E64: =VLOOKUP(S64,Data!$B:$E,4,FALSE) -> #N/A | F64: =VLOOKUP(T64,Data!$B:$E,4,FALSE) -> #N/A | G64: =VLOOKUP(U64,Data!$B:$E,4,FALSE) -> #N/A | H64: =VLOOKUP(V64,Data!$B:$E,4,FALSE) -> #N/A | I64: =VLOOKUP(W64,Data!$B:$E,4,FALSE) -> #N/A | J64: =VLOOKUP(X64,Data!$B:$E,4,FALSE) -> #N/A | O64: YZF R1M | P64: A1380 | Q64: A1380.1 | R64: A1380.2 | S64: A1380.8 | T64: A1380.3 | U64: A1380.4 | V64: A1380.5 | W64: A1380.6 | X64: A1380.7
A65: XT1200Z DX | B65: A1385 | C65: =VLOOKUP(Q65,Data!$B:$E,4,FALSE) -> #N/A | D65: =VLOOKUP(R65,Data!$B:$E,4,FALSE) -> #N/A | E65: =VLOOKUP(S65,Data!$B:$E,4,FALSE) -> #N/A | F65: =VLOOKUP(T65,Data!$B:$E,4,FALSE) -> #N/A | G65: =VLOOKUP(U65,Data!$B:$E,4,FALSE) -> #N/A | H65: =VLOOKUP(V65,Data!$B:$E,4,FALSE) -> #N/A | I65: =VLOOKUP(W65,Data!$B:$E,4,FALSE) -> #N/A | J65: =VLOOKUP(X65,Data!$B:$E,4,FALSE) -> #N/A | O65: XT1200Z DX | P65: A1385 | Q65: A1385.1 | R65: A1385.2 | S65: A1385.8 | T65: A1385.3 | U65: A1385.4 | V65: A1385.5 | W65: A1385.6 | X65: A1385.7
A66: TRACER 900 GT | B66: A1386 | C66: =VLOOKUP(Q66,Data!$B:$E,4,FALSE) -> #N/A | D66: =VLOOKUP(R66,Data!$B:$E,4,FALSE) -> #N/A | E66: =VLOOKUP(S66,Data!$B:$E,4,FALSE) -> #N/A | F66: =VLOOKUP(T66,Data!$B:$E,4,FALSE) -> #N/A | G66: =VLOOKUP(U66,Data!$B:$E,4,FALSE) -> #N/A | H66: =VLOOKUP(V66,Data!$B:$E,4,FALSE) -> #N/A | I66: =VLOOKUP(W66,Data!$B:$E,4,FALSE) -> #N/A | J66: =VLOOKUP(X66,Data!$B:$E,4,FALSE) -> #N/A | O66: TRACER 900 GT | P66: A1386 | Q66: A1386.1 | R66: A1386.2 | S66: A1386.8 | T66: A1386.3 | U66: A1386.4 | V66: A1386.5 | W66: A1386.6 | X66: A1386.7
A67: XTZ690 TENERE | B67: A1387 | C67: =VLOOKUP(Q67,Data!$B:$E,4,FALSE) -> #N/A | D67: =VLOOKUP(R67,Data!$B:$E,4,FALSE) -> #N/A | E67: =VLOOKUP(S67,Data!$B:$E,4,FALSE) -> #N/A | F67: =VLOOKUP(T67,Data!$B:$E,4,FALSE) -> #N/A | G67: =VLOOKUP(U67,Data!$B:$E,4,FALSE) -> #N/A | H67: =VLOOKUP(V67,Data!$B:$E,4,FALSE) -> #N/A | I67: =VLOOKUP(W67,Data!$B:$E,4,FALSE) -> #N/A | J67: =VLOOKUP(X67,Data!$B:$E,4,FALSE) -> #N/A | O67: XTZ690 TENERE | P67: A1387 | Q67: A1387.1 | R67: A1387.2 | S67: A1387.8 | T67: A1387.3 | U67: A1387.4 | V67: A1387.5 | W67: A1387.6 | X67: A1387.7
A68: =Translation!A88 -> TOTAL DE VENDAS - LINHA > 500 cc | B68: A1390 | C68: =VLOOKUP(Q68,Data!$B:$E,4,FALSE) -> #N/A | D68: =VLOOKUP(R68,Data!$B:$E,4,FALSE) -> #N/A | E68: =VLOOKUP(S68,Data!$B:$E,4,FALSE) -> #N/A | F68: =VLOOKUP(T68,Data!$B:$E,4,FALSE) -> #N/A | G68: =VLOOKUP(U68,Data!$B:$E,4,FALSE) -> #N/A | H68: =VLOOKUP(V68,Data!$B:$E,4,FALSE) -> #N/A | I68: =VLOOKUP(W68,Data!$B:$E,4,FALSE) -> #N/A | J68: =VLOOKUP(X68,Data!$B:$E,4,FALSE) -> #N/A | O68: TOTAL DE VENDAS - LINHA > 500 cc | P68: A1390 | Q68: A1390.1 | R68: A1390.2 | S68: A1390.8 | T68: A1390.3 | U68: A1390.4 | V68: A1390.5 | W68: A1390.6 | X68: A1390.7
A69: =Translation!A89 -> TOTAL OUTROS | B69: A1399 | C69: =VLOOKUP(Q69,Data!$B:$E,4,FALSE) -> #N/A | D69: =VLOOKUP(R69,Data!$B:$E,4,FALSE) -> #N/A | E69: =VLOOKUP(S69,Data!$B:$E,4,FALSE) -> #N/A | F69: =VLOOKUP(T69,Data!$B:$E,4,FALSE) -> #N/A | G69: =VLOOKUP(U69,Data!$B:$E,4,FALSE) -> #N/A | H69: =VLOOKUP(V69,Data!$B:$E,4,FALSE) -> #N/A | I69: =VLOOKUP(W69,Data!$B:$E,4,FALSE) -> #N/A | J69: =VLOOKUP(X69,Data!$B:$E,4,FALSE) -> #N/A | O69: TOTAL (NÃO ABERTO) | P69: A1399 | Q69: A1399.1 | R69: A1399.2 | S69: A1399.8 | T69: A1399.3 | U69: A1399.4 | V69: A1399.5 | W69: A1399.6 | X69: A1399.7
A70: =Translation!A90 -> TOTAL DE VENDAS DE NOVOS - MOTOCICLETAS | B70: A1400 | C70: =VLOOKUP(Q70,Data!$B:$E,4,FALSE) -> #N/A | D70: =VLOOKUP(R70,Data!$B:$E,4,FALSE) -> #N/A | E70: =VLOOKUP(S70,Data!$B:$E,4,FALSE) -> #N/A | F70: =VLOOKUP(T70,Data!$B:$E,4,FALSE) -> #N/A | G70: =VLOOKUP(U70,Data!$B:$E,4,FALSE) -> #N/A | H70: =VLOOKUP(V70,Data!$B:$E,4,FALSE) -> #N/A | I70: =VLOOKUP(W70,Data!$B:$E,4,FALSE) -> #N/A | J70: =VLOOKUP(X70,Data!$B:$E,4,FALSE) -> #N/A | O70: TOTAL DE VENDAS DE NOVOS - MOTOCICLETAS | P70: A1400 | Q70: A1400.1 | R70: A1400.2 | S70: A1400.8 | T70: A1400.3 | U70: A1400.4 | V70: A1400.5 | W70: A1400.6 | X70: A1400.7
A71: =Translation!A91 -> LINHA NÁUTICA | B71: =Translation!$G$32 -> CONTA | C71: =Translation!$G$12 -> UNIDADES | D71: =Translation!$G$11 -> RECEITA (SEM IMPOSTOS) | E71: =Translation!$G$33 -> UNIDADES DEVOLVIDAS | F71: =Translation!$G$14 -> DEVOLUÇÃO DE VENDAS | G71: =Translation!$G$3 -> ABAT. E DESCONTO | H71: =Translation!$G$9 -> RECEITA LÍQUIDA | I71: =Translation!$G$2 -> CUSTO | J71: =Translation!$G$5 -> LUCRO BRUTO | O71: LINHA NÁUTICA | P71: =Translation!$G$32 -> CONTA | Q71: UNITS | R71: SALES | S71: URETURN | T71: SC | U71: DISC | V71: NS | W71: COS | X71: GP
A72: =Translation!A92 -> MOTORES | B72: A1700 | C72: =VLOOKUP(Q72,Data!$B:$E,4,FALSE) -> #N/A | D72: =VLOOKUP(R72,Data!$B:$E,4,FALSE) -> #N/A | E72: =VLOOKUP(S72,Data!$B:$E,4,FALSE) -> #N/A | F72: =VLOOKUP(T72,Data!$B:$E,4,FALSE) -> #N/A | G72: =VLOOKUP(U72,Data!$B:$E,4,FALSE) -> #N/A | H72: =VLOOKUP(V72,Data!$B:$E,4,FALSE) -> #N/A | I72: =VLOOKUP(W72,Data!$B:$E,4,FALSE) -> #N/A | J72: =VLOOKUP(X72,Data!$B:$E,4,FALSE) -> #N/A | O72: MOTORES | P72: A1700 | Q72: A1700.1 | R72: A1700.2 | S72: A1700.8 | T72: A1700.3 | U72: A1700.4 | V72: A1700.5 | W72: A1700.6 | X72: A1700.7
A73: =Translation!A93 -> WAVERUNNER | B73: A1710 | C73: =VLOOKUP(Q73,Data!$B:$E,4,FALSE) -> #N/A | D73: =VLOOKUP(R73,Data!$B:$E,4,FALSE) -> #N/A | E73: =VLOOKUP(S73,Data!$B:$E,4,FALSE) -> #N/A | F73: =VLOOKUP(T73,Data!$B:$E,4,FALSE) -> #N/A | G73: =VLOOKUP(U73,Data!$B:$E,4,FALSE) -> #N/A | H73: =VLOOKUP(V73,Data!$B:$E,4,FALSE) -> #N/A | I73: =VLOOKUP(W73,Data!$B:$E,4,FALSE) -> #N/A | J73: =VLOOKUP(X73,Data!$B:$E,4,FALSE) -> #N/A | O73: WAVERUNNER | P73: A1710 | Q73: A1710.1 | R73: A1710.2 | S73: A1710.8 | T73: A1710.3 | U73: A1710.4 | V73: A1710.5 | W73: A1710.6 | X73: A1710.7
A74: =Translation!A94 -> TOTAL DE VENDAS - LINHA NAÚTICA | B74: A1720 | C74: =VLOOKUP(Q74,Data!$B:$E,4,FALSE) -> #N/A | D74: =VLOOKUP(R74,Data!$B:$E,4,FALSE) -> #N/A | E74: =VLOOKUP(S74,Data!$B:$E,4,FALSE) -> #N/A | F74: =VLOOKUP(T74,Data!$B:$E,4,FALSE) -> #N/A | G74: =VLOOKUP(U74,Data!$B:$E,4,FALSE) -> #N/A | H74: =VLOOKUP(V74,Data!$B:$E,4,FALSE) -> #N/A | I74: =VLOOKUP(W74,Data!$B:$E,4,FALSE) -> #N/A | J74: =VLOOKUP(X74,Data!$B:$E,4,FALSE) -> #N/A | O74: TOTAL DE VENDAS - LINHA NAÚTICA | P74: A1720 | Q74: A1720.1 | R74: A1720.2 | S74: A1720.8 | T74: A1720.3 | U74: A1720.4 | V74: A1720.5 | W74: A1720.6 | X74: A1720.7
A75: =Translation!A95 -> LINHA QUADRICICLOS | B75: =Translation!$G$32 -> CONTA | C75: =Translation!$G$12 -> UNIDADES | D75: =Translation!$G$11 -> RECEITA (SEM IMPOSTOS) | E75: =Translation!$G$33 -> UNIDADES DEVOLVIDAS | F75: =Translation!$G$14 -> DEVOLUÇÃO DE VENDAS | G75: =Translation!$G$3 -> ABAT. E DESCONTO | H75: =Translation!$G$9 -> RECEITA LÍQUIDA | I75: =Translation!$G$2 -> CUSTO | J75: =Translation!$G$5 -> LUCRO BRUTO | O75: LINHA QUADRICICLOS | P75: =Translation!$G$32 -> CONTA | Q75: UNITS | R75: SALES | S75: URETURN | T75: SC | U75: DISC | V75: NS | W75: COS | X75: GP
A76: =Translation!A96 -> MODELO 1 | B76: A1800 | C76: =VLOOKUP(Q76,Data!$B:$E,4,FALSE) -> #N/A | D76: =VLOOKUP(R76,Data!$B:$E,4,FALSE) -> #N/A | E76: =VLOOKUP(S76,Data!$B:$E,4,FALSE) -> #N/A | F76: =VLOOKUP(T76,Data!$B:$E,4,FALSE) -> #N/A | G76: =VLOOKUP(U76,Data!$B:$E,4,FALSE) -> #N/A | H76: =VLOOKUP(V76,Data!$B:$E,4,FALSE) -> #N/A | I76: =VLOOKUP(W76,Data!$B:$E,4,FALSE) -> #N/A | J76: =VLOOKUP(X76,Data!$B:$E,4,FALSE) -> #N/A | O76: MODELO 1 | P76: A1800 | Q76: A1800.1 | R76: A1800.2 | S76: A1800.8 | T76: A1800.3 | U76: A1800.4 | V76: A1800.5 | W76: A1800.6 | X76: A1800.7
A77: =Translation!A97 -> MODELO 2 | B77: A1810 | C77: =VLOOKUP(Q77,Data!$B:$E,4,FALSE) -> #N/A | D77: =VLOOKUP(R77,Data!$B:$E,4,FALSE) -> #N/A | E77: =VLOOKUP(S77,Data!$B:$E,4,FALSE) -> #N/A | F77: =VLOOKUP(T77,Data!$B:$E,4,FALSE) -> #N/A | G77: =VLOOKUP(U77,Data!$B:$E,4,FALSE) -> #N/A | H77: =VLOOKUP(V77,Data!$B:$E,4,FALSE) -> #N/A | I77: =VLOOKUP(W77,Data!$B:$E,4,FALSE) -> #N/A | J77: =VLOOKUP(X77,Data!$B:$E,4,FALSE) -> #N/A | O77: MODELO 2 | P77: A1810 | Q77: A1810.1 | R77: A1810.2 | S77: A1810.8 | T77: A1810.3 | U77: A1810.4 | V77: A1810.5 | W77: A1810.6 | X77: A1810.7
A78: =Translation!A98 -> MODELO 3 | B78: A1820 | C78: =VLOOKUP(Q78,Data!$B:$E,4,FALSE) -> #N/A | D78: =VLOOKUP(R78,Data!$B:$E,4,FALSE) -> #N/A | E78: =VLOOKUP(S78,Data!$B:$E,4,FALSE) -> #N/A | F78: =VLOOKUP(T78,Data!$B:$E,4,FALSE) -> #N/A | G78: =VLOOKUP(U78,Data!$B:$E,4,FALSE) -> #N/A | H78: =VLOOKUP(V78,Data!$B:$E,4,FALSE) -> #N/A | I78: =VLOOKUP(W78,Data!$B:$E,4,FALSE) -> #N/A | J78: =VLOOKUP(X78,Data!$B:$E,4,FALSE) -> #N/A | O78: MODELO 3 | P78: A1820 | Q78: A1820.1 | R78: A1820.2 | S78: A1820.8 | T78: A1820.3 | U78: A1820.4 | V78: A1820.5 | W78: A1820.6 | X78: A1820.7
A79: =Translation!A99 -> TOTAL DE VENDAS - LINHA QUADRICICLOS | B79: A1830 | C79: =VLOOKUP(Q79,Data!$B:$E,4,FALSE) -> #N/A | D79: =VLOOKUP(R79,Data!$B:$E,4,FALSE) -> #N/A | E79: =VLOOKUP(S79,Data!$B:$E,4,FALSE) -> #N/A | F79: =VLOOKUP(T79,Data!$B:$E,4,FALSE) -> #N/A | G79: =VLOOKUP(U79,Data!$B:$E,4,FALSE) -> #N/A | H79: =VLOOKUP(V79,Data!$B:$E,4,FALSE) -> #N/A | I79: =VLOOKUP(W79,Data!$B:$E,4,FALSE) -> #N/A | J79: =VLOOKUP(X79,Data!$B:$E,4,FALSE) -> #N/A | O79: TOTAL DE VENDAS - LINHA QUADRICICLOS | P79: A1830 | Q79: A1830.1 | R79: A1830.2 | S79: A1830.8 | T79: A1830.3 | U79: A1830.4 | V79: A1830.5 | W79: A1830.6 | X79: A1830.7
A80: =Translation!A100 -> TOTAL DE VENDAS DE VEÍCULOS | B80: A1840 | C80: =VLOOKUP(Q80,Data!$B:$E,4,FALSE) -> #N/A | D80: =VLOOKUP(R80,Data!$B:$E,4,FALSE) -> #N/A | E80: =VLOOKUP(S80,Data!$B:$E,4,FALSE) -> #N/A | F80: =VLOOKUP(T80,Data!$B:$E,4,FALSE) -> #N/A | G80: =VLOOKUP(U80,Data!$B:$E,4,FALSE) -> #N/A | H80: =VLOOKUP(V80,Data!$B:$E,4,FALSE) -> #N/A | I80: =VLOOKUP(W80,Data!$B:$E,4,FALSE) -> #N/A | J80: =VLOOKUP(X80,Data!$B:$E,4,FALSE) -> #N/A | O80: TOTAL DE VENDAS DE VEÍCULOS | P80: A1840 | Q80: A1840.1 | R80: A1840.2 | S80: A1840.8 | T80: A1840.3 | U80: A1840.4 | V80: A1840.5 | W80: A1840.6 | X80: A1840.7
A81: =Translation!A101 -> OUTRAS RECEITAS OPERACIONAIS | B81: =Translation!$G$32 -> CONTA | C81: =Translation!$G$1 -> VALOR | O81: OUTRAS RECEITAS OPERACIONAIS | P81: =Translation!$G$32 -> CONTA | Q81: =Translation!$G$1 -> VALOR
A82: =Translation!A102 -> INCENTIVOS DE VAREJO | B82: A3000 | C82: =VLOOKUP(Q82,Data!$B:$E,4,FALSE) -> #N/A | O82: INCENTIVOS DE VAREJO | P82: A3000 | Q82: A3000.1
A83: =Translation!A103 -> BONIFICAÇÕES 1 | B83: A3010 | C83: =VLOOKUP(Q83,Data!$B:$E,4,FALSE) -> #N/A | O83: BONIFICAÇÕES 1 | P83: A3010 | Q83: A3010.1
A84: =Translation!A104 -> BONIFICAÇÕES 2 | B84: A3020 | C84: =VLOOKUP(Q84,Data!$B:$E,4,FALSE) -> #N/A | O84: BONIFICAÇÕES 2 | P84: A3020 | Q84: A3020.1
A85: =Translation!A105 -> COMISSÕES DIVERSAS | B85: A3030 | C85: =VLOOKUP(Q85,Data!$B:$E,4,FALSE) -> #N/A | O85: COMISSÕES DIVERSAS | P85: A3030 | Q85: A3030.1
A86: =Translation!A106 -> OUTRAS RECEITAS | B86: A3040 | C86: =VLOOKUP(Q86,Data!$B:$E,4,FALSE) -> #N/A | O86: OUTRAS RECEITAS | P86: A3040 | Q86: A3040.1
A87: =Translation!A107 -> TOTAL DE OUTRAS RECEITAS OPERACIONAIS | B87: A3090 | C87: =VLOOKUP(Q87,Data!$B:$E,4,FALSE) -> #N/A | O87: TOTAL DE OUTRAS RECEITAS OPERACIONAIS | P87: A3090 | Q87: A3090.1
A88: =Translation!A108 -> DESPESAS VARIÁVEIS | B88: =Translation!$G$32 -> CONTA | C88: =Translation!$G$1 -> VALOR | O88: DESPESAS VARIÁVEIS | P88: =Translation!$G$32 -> CONTA | Q88: =Translation!$G$1 -> VALOR
A89: =Translation!A109 -> COMISSÕES SOBRE VENDAS | B89: A3100 | C89: =VLOOKUP(Q89,Data!$B:$E,4,FALSE) -> #N/A | O89: COMISSÕES SOBRE VENDAS | P89: A3100 | Q89: A3100.1
A90: =Translation!A110 -> ENCARGOS SOBRE COMISSÕES (-) | B90: A3110 | C90: =VLOOKUP(Q90,Data!$B:$E,4,FALSE) -> #N/A | O90: ENCARGOS SOBRE COMISSÕES (-) | P90: A3110 | Q90: A3110.1
A91: =Translation!A111 -> OUTRAS DESPESAS | B91: A3120 | C91: =VLOOKUP(Q91,Data!$B:$E,4,FALSE) -> #N/A | O91: OUTRAS DESPESAS | P91: A3120 | Q91: A3120.1
A92: =Translation!A112 -> TOTAL DE DESPESAS VARIÁVEIS | B92: A3130 | C92: =VLOOKUP(Q92,Data!$B:$E,4,FALSE) -> #N/A | O92: TOTAL DE DESPESAS VARIÁVEIS | P92: A3130 | Q92: A3130.1
A93: =Translation!A113 -> MARGEM DE CONTRIBUIÇÃO | B93: =Translation!$G$32 -> CONTA | C93: =Translation!$G$1 -> VALOR | O93: MARGEM DE CONTRIBUIÇÃO | P93: =Translation!$G$32 -> CONTA | Q93: =Translation!$G$1 -> VALOR
A94: =Translation!A114 -> MARGEM DE CONTRIBUIÇÃO | B94: A3500 | C94: =VLOOKUP(Q94,Data!$B:$E,4,FALSE) -> #N/A | O94: MARGEM DE CONTRIBUIÇÃO | P94: A3500 | Q94: A3500.1
A95: =Translation!A115 -> DESPESAS | B95: =Translation!$G$32 -> CONTA | C95: =Translation!$G$1 -> VALOR | O95: DESPESAS | P95: =Translation!$G$32 -> CONTA | Q95: =Translation!$G$1 -> VALOR
A96: =Translation!A116 -> TOTAL DE DESPESAS COM PESSOAL (A) | B96: A4090 | C96: =VLOOKUP(Q96,Data!$B:$E,4,FALSE) -> #N/A | O96: TOTAL DE DESPESAS COM PESSOAL (A) | P96: A4090 | Q96: A4090.1
A97: =Translation!A117 -> TOTAL DE DESPESAS COM ESTRUTURA - IMÓVEIS (B) | B97: A4170 | C97: =VLOOKUP(Q97,Data!$B:$E,4,FALSE) -> #N/A | O97: TOTAL DE DESPESAS COM ESTRUTURA - IMÓVEIS (B) | P97: A4170 | Q97: A4170.1
A98: =Translation!A118 -> TOTAL DE DESPESAS GERAIS (C) | B98: A4370 | C98: =VLOOKUP(Q98,Data!$B:$E,4,FALSE) -> #N/A | O98: TOTAL DE DESPESAS GERAIS (C) | P98: A4370 | Q98: A4370.1
A99: =Translation!A119 -> TOTAL DE DESPESAS FIXAS (A+B+C) | B99: A4380 | C99: =VLOOKUP(Q99,Data!$B:$E,4,FALSE) -> #N/A | O99: TOTAL DE DESPESAS OPERACIONAIS (A + B + C) | P99: A4380 | Q99: A4380.1
A100: =Translation!A120 -> LUCRO / PREJUÍZO OPERACIONAL | B100: =Translation!$G$32 -> CONTA | C100: =Translation!$G$1 -> VALOR | O100: LUCRO / PREJUÍZO OPERACIONAL | P100: =Translation!$G$32 -> CONTA | Q100: =Translation!$G$1 -> VALOR
...

Sheet DRE Mês
A1: =Translation!$A$23 -> DRE YAMAHA BMI - Mês
A2: =Translation!$A$20&Data!D1 -> Concessionário: %%=$RecordSet.#4 | C2: =Translation!$A$19&Data!D3 -> Localização: %%=$RecordSet.#8 | H2: =Translation!$A$21 -> Período: | I2: =VLOOKUP(Data!D6,Data!H1:I12,2,FALSE)&" "&Data!E6 -> #N/A
A3: =Translation!A1 -> VENDA DE NOVOS | O3: VENDA NOVOS
A4: =Translation!A35 -> LINHA SCOOTER <200 cc | B4: =Translation!$G$32 -> CONTA | C4: =Translation!$G$12 -> UNIDADES | D4: =Translation!$G$11 -> RECEITA (SEM IMPOSTOS) | E4: =Translation!$G$33 -> UNIDADES DEVOLVIDAS | F4: =Translation!$G$14 -> DEVOLUÇÃO DE VENDAS | G4: =Translation!$G$3 -> ABAT. E DESCONTO | H4: =Translation!$G$9 -> RECEITA LÍQUIDA | I4: =Translation!$G$2 -> CUSTO | J4: =Translation!$G$5 -> LUCRO BRUTO | O4: LINHA SCOOTER <200 cc | P4: =Translation!$G$32 -> CONTA | Q4: UNITS | R4: SALES | S4: URETURN | T4: SC | U4: DISC | V4: NS | W4: COS | X4: GP
A5: =Translation!A36 -> NEO 125 | B5: A1000 | C5: =VLOOKUP(Q5,Data!$B:$E,3,FALSE) -> #N/A | D5: =VLOOKUP(R5,Data!$B:$E,3,FALSE) -> #N/A | E5: =VLOOKUP(S5,Data!$B:$E,3,FALSE) -> #N/A | F5: =VLOOKUP(T5,Data!$B:$E,3,FALSE) -> #N/A | G5: =VLOOKUP(U5,Data!$B:$E,3,FALSE) -> #N/A | H5: =VLOOKUP(V5,Data!$B:$E,3,FALSE) -> #N/A | I5: =VLOOKUP(W5,Data!$B:$E,3,FALSE) -> #N/A | J5: =VLOOKUP(X5,Data!$B:$E,3,FALSE) -> #N/A | O5: NEO 125 | P5: A1000 | Q5: A1000.1 | R5: A1000.2 | S5: A1000.8 | T5: A1000.3 | U5: A1000.4 | V5: A1000.5 | W5: A1000.6 | X5: A1000.7
A6: =Translation!A37 -> NMAX 160 ABS | B6: A1010 | C6: =VLOOKUP(Q6,Data!$B:$E,3,FALSE) -> #N/A | D6: =VLOOKUP(R6,Data!$B:$E,3,FALSE) -> #N/A | E6: =VLOOKUP(S6,Data!$B:$E,3,FALSE) -> #N/A | F6: =VLOOKUP(T6,Data!$B:$E,3,FALSE) -> #N/A | G6: =VLOOKUP(U6,Data!$B:$E,3,FALSE) -> #N/A | H6: =VLOOKUP(V6,Data!$B:$E,3,FALSE) -> #N/A | I6: =VLOOKUP(W6,Data!$B:$E,3,FALSE) -> #N/A | J6: =VLOOKUP(X6,Data!$B:$E,3,FALSE) -> #N/A | O6: NMAX 160 ABS | P6: A1010 | Q6: A1010.1 | R6: A1010.2 | S6: A1010.8 | T6: A1010.3 | U6: A1010.4 | V6: A1010.5 | W6: A1010.6 | X6: A1010.7
A7: =Translation!A38 -> LINHA SCOOTER >200 cc | B7: =Translation!$G$32 -> CONTA | C7: =Translation!$G$12 -> UNIDADES | D7: =Translation!$G$11 -> RECEITA (SEM IMPOSTOS) | E7: =Translation!$G$33 -> UNIDADES DEVOLVIDAS | F7: =Translation!$G$14 -> DEVOLUÇÃO DE VENDAS | G7: =Translation!$G$3 -> ABAT. E DESCONTO | H7: =Translation!$G$9 -> RECEITA LÍQUIDA | I7: =Translation!$G$2 -> CUSTO | J7: =Translation!$G$5 -> LUCRO BRUTO | O7: LINHA SCOOTER >200 cc | P7: =Translation!$G$32 -> CONTA | Q7: UNITS | R7: SALES | S7: URETURN | T7: SC | U7: DISC | V7: NS | W7: COS | X7: GP
A8: =Translation!A39 -> TMAX 530 | B8: A1020 | C8: =VLOOKUP(Q8,Data!$B:$E,3,FALSE) -> #N/A | D8: =VLOOKUP(R8,Data!$B:$E,3,FALSE) -> #N/A | E8: =VLOOKUP(S8,Data!$B:$E,3,FALSE) -> #N/A | F8: =VLOOKUP(T8,Data!$B:$E,3,FALSE) -> #N/A | G8: =VLOOKUP(U8,Data!$B:$E,3,FALSE) -> #N/A | H8: =VLOOKUP(V8,Data!$B:$E,3,FALSE) -> #N/A | I8: =VLOOKUP(W8,Data!$B:$E,3,FALSE) -> #N/A | J8: =VLOOKUP(X8,Data!$B:$E,3,FALSE) -> #N/A | O8: TMAX 530 | P8: A1020 | Q8: A1020.1 | R8: A1020.2 | S8: A1020.8 | T8: A1020.3 | U8: A1020.4 | V8: A1020.5 | W8: A1020.6 | X8: A1020.7
A9: X MAX ABS | B9: A1021 | C9: =VLOOKUP(Q9,Data!$B:$E,3,FALSE) -> #N/A | D9: =VLOOKUP(R9,Data!$B:$E,3,FALSE) -> #N/A | E9: =VLOOKUP(S9,Data!$B:$E,3,FALSE) -> #N/A | F9: =VLOOKUP(T9,Data!$B:$E,3,FALSE) -> #N/A | G9: =VLOOKUP(U9,Data!$B:$E,3,FALSE) -> #N/A | H9: =VLOOKUP(V9,Data!$B:$E,3,FALSE) -> #N/A | I9: =VLOOKUP(W9,Data!$B:$E,3,FALSE) -> #N/A | J9: =VLOOKUP(X9,Data!$B:$E,3,FALSE) -> #N/A | O9: X MAX ABS | P9: A1021 | Q9: A1021.1 | R9: A1021.2 | S9: A1021.8 | T9: A1021.3 | U9: A1021.4 | V9: A1021.5 | W9: A1021.6 | X9: A1021.7
A10: NEOS CONNECTED | B10: A1022 | C10: =VLOOKUP(Q10,Data!$B:$E,3,FALSE) -> #N/A | D10: =VLOOKUP(R10,Data!$B:$E,3,FALSE) -> #N/A | E10: =VLOOKUP(S10,Data!$B:$E,3,FALSE) -> #N/A | F10: =VLOOKUP(T10,Data!$B:$E,3,FALSE) -> #N/A | G10: =VLOOKUP(U10,Data!$B:$E,3,FALSE) -> #N/A | H10: =VLOOKUP(V10,Data!$B:$E,3,FALSE) -> #N/A | I10: =VLOOKUP(W10,Data!$B:$E,3,FALSE) -> #N/A | J10: =VLOOKUP(X10,Data!$B:$E,3,FALSE) -> #N/A | O10: NEOS CONNECTED | P10: A1022 | Q10: A1022.1 | R10: A1022.2 | S10: A1022.8 | T10: A1022.3 | U10: A1022.4 | V10: A1022.5 | W10: A1022.6 | X10: A1022.7
A11: =Translation!A40 -> TOTAL DE VENDAS - SCOOTER | B11: A1030 | C11: =VLOOKUP(Q11,Data!$B:$E,3,FALSE) -> #N/A | D11: =VLOOKUP(R11,Data!$B:$E,3,FALSE) -> #N/A | E11: =VLOOKUP(S11,Data!$B:$E,3,FALSE) -> #N/A | F11: =VLOOKUP(T11,Data!$B:$E,3,FALSE) -> #N/A | G11: =VLOOKUP(U11,Data!$B:$E,3,FALSE) -> #N/A | H11: =VLOOKUP(V11,Data!$B:$E,3,FALSE) -> #N/A | I11: =VLOOKUP(W11,Data!$B:$E,3,FALSE) -> #N/A | J11: =VLOOKUP(X11,Data!$B:$E,3,FALSE) -> #N/A | O11: TOTAL DE VENDAS - SCOOTER | P11: A1030 | Q11: A1030.1 | R11: A1030.2 | S11: A1030.8 | T11: A1030.3 | U11: A1030.4 | V11: A1030.5 | W11: A1030.6 | X11: A1030.7
A12: =Translation!A41 -> LINHA OFF ROAD | B12: =Translation!$G$32 -> CONTA | C12: =Translation!$G$12 -> UNIDADES | D12: =Translation!$G$11 -> RECEITA (SEM IMPOSTOS) | E12: =Translation!$G$33 -> UNIDADES DEVOLVIDAS | F12: =Translation!$G$14 -> DEVOLUÇÃO DE VENDAS | G12: =Translation!$G$3 -> ABAT. E DESCONTO | H12: =Translation!$G$9 -> RECEITA LÍQUIDA | I12: =Translation!$G$2 -> CUSTO | J12: =Translation!$G$5 -> LUCRO BRUTO | O12: LINHA OFF ROAD | P12: =Translation!$G$32 -> CONTA | Q12: UNITS | R12: SALES | S12: URETURN | T12: SC | U12: DISC | V12: NS | W12: COS | X12: GP
A13: =Translation!A42 -> TTR 230 | B13: A1040 | C13: =VLOOKUP(Q13,Data!$B:$E,3,FALSE) -> #N/A | D13: =VLOOKUP(R13,Data!$B:$E,3,FALSE) -> #N/A | E13: =VLOOKUP(S13,Data!$B:$E,3,FALSE) -> #N/A | F13: =VLOOKUP(T13,Data!$B:$E,3,FALSE) -> #N/A | G13: =VLOOKUP(U13,Data!$B:$E,3,FALSE) -> #N/A | H13: =VLOOKUP(V13,Data!$B:$E,3,FALSE) -> #N/A | I13: =VLOOKUP(W13,Data!$B:$E,3,FALSE) -> #N/A | J13: =VLOOKUP(X13,Data!$B:$E,3,FALSE) -> #N/A | O13: TTR 230 | P13: A1040 | Q13: A1040.1 | R13: A1040.2 | S13: A1040.8 | T13: A1040.3 | U13: A1040.4 | V13: A1040.5 | W13: A1040.6 | X13: A1040.7
A14: YZ 85LW | B14: A1045 | C14: =VLOOKUP(Q14,Data!$B:$E,3,FALSE) -> #N/A | D14: =VLOOKUP(R14,Data!$B:$E,3,FALSE) -> #N/A | E14: =VLOOKUP(S14,Data!$B:$E,3,FALSE) -> #N/A | F14: =VLOOKUP(T14,Data!$B:$E,3,FALSE) -> #N/A | G14: =VLOOKUP(U14,Data!$B:$E,3,FALSE) -> #N/A | H14: =VLOOKUP(V14,Data!$B:$E,3,FALSE) -> #N/A | I14: =VLOOKUP(W14,Data!$B:$E,3,FALSE) -> #N/A | J14: =VLOOKUP(X14,Data!$B:$E,3,FALSE) -> #N/A | O14: YZ 85LW | P14: A1045 | Q14: A1045.1 | R14: A1045.2 | S14: A1045.8 | T14: A1045.3 | U14: A1045.4 | V14: A1045.5 | W14: A1045.6 | X14: A1045.7
A15: =Translation!A44 -> YZ 250 | B15: A1050 | C15: =VLOOKUP(Q15,Data!$B:$E,3,FALSE) -> #N/A | D15: =VLOOKUP(R15,Data!$B:$E,3,FALSE) -> #N/A | E15: =VLOOKUP(S15,Data!$B:$E,3,FALSE) -> #N/A | F15: =VLOOKUP(T15,Data!$B:$E,3,FALSE) -> #N/A | G15: =VLOOKUP(U15,Data!$B:$E,3,FALSE) -> #N/A | H15: =VLOOKUP(V15,Data!$B:$E,3,FALSE) -> #N/A | I15: =VLOOKUP(W15,Data!$B:$E,3,FALSE) -> #N/A | J15: =VLOOKUP(X15,Data!$B:$E,3,FALSE) -> #N/A | O15: YZ 250 | P15: A1050 | Q15: A1050.1 | R15: A1050.2 | S15: A1050.8 | T15: A1050.3 | U15: A1050.4 | V15: A1050.5 | W15: A1050.6 | X15: A1050.7
A16: =Translation!A45 -> YZ 250F | B16: A1060 | C16: =VLOOKUP(Q16,Data!$B:$E,3,FALSE) -> #N/A | D16: =VLOOKUP(R16,Data!$B:$E,3,FALSE) -> #N/A | E16: =VLOOKUP(S16,Data!$B:$E,3,FALSE) -> #N/A | F16: =VLOOKUP(T16,Data!$B:$E,3,FALSE) -> #N/A | G16: =VLOOKUP(U16,Data!$B:$E,3,FALSE) -> #N/A | H16: =VLOOKUP(V16,Data!$B:$E,3,FALSE) -> #N/A | I16: =VLOOKUP(W16,Data!$B:$E,3,FALSE) -> #N/A | J16: =VLOOKUP(X16,Data!$B:$E,3,FALSE) -> #N/A | O16: YZ 250F | P16: A1060 | Q16: A1060.1 | R16: A1060.2 | S16: A1060.8 | T16: A1060.3 | U16: A1060.4 | V16: A1060.5 | W16: A1060.6 | X16: A1060.7
A17: =Translation!A46 -> YZ 250FX | B17: A1070 | C17: =VLOOKUP(Q17,Data!$B:$E,3,FALSE) -> #N/A | D17: =VLOOKUP(R17,Data!$B:$E,3,FALSE) -> #N/A | E17: =VLOOKUP(S17,Data!$B:$E,3,FALSE) -> #N/A | F17: =VLOOKUP(T17,Data!$B:$E,3,FALSE) -> #N/A | G17: =VLOOKUP(U17,Data!$B:$E,3,FALSE) -> #N/A | H17: =VLOOKUP(V17,Data!$B:$E,3,FALSE) -> #N/A | I17: =VLOOKUP(W17,Data!$B:$E,3,FALSE) -> #N/A | J17: =VLOOKUP(X17,Data!$B:$E,3,FALSE) -> #N/A | O17: YZ 250FX | P17: A1070 | Q17: A1070.1 | R17: A1070.2 | S17: A1070.8 | T17: A1070.3 | U17: A1070.4 | V17: A1070.5 | W17: A1070.6 | X17: A1070.7
A18: YZ 250X | B18: A1075 | C18: =VLOOKUP(Q18,Data!$B:$E,3,FALSE) -> #N/A | D18: =VLOOKUP(R18,Data!$B:$E,3,FALSE) -> #N/A | E18: =VLOOKUP(S18,Data!$B:$E,3,FALSE) -> #N/A | F18: =VLOOKUP(T18,Data!$B:$E,3,FALSE) -> #N/A | G18: =VLOOKUP(U18,Data!$B:$E,3,FALSE) -> #N/A | H18: =VLOOKUP(V18,Data!$B:$E,3,FALSE) -> #N/A | I18: =VLOOKUP(W18,Data!$B:$E,3,FALSE) -> #N/A | J18: =VLOOKUP(X18,Data!$B:$E,3,FALSE) -> #N/A | O18: YZ 250X | P18: A1075 | Q18: A1075.1 | R18: A1075.2 | S18: A1075.8 | T18: A1075.3 | U18: A1075.4 | V18: A1075.5 | W18: A1075.6 | X18: A1075.7
A19: =Translation!A48 -> YZ 450F | B19: A1080 | C19: =VLOOKUP(Q19,Data!$B:$E,3,FALSE) -> #N/A | D19: =VLOOKUP(R19,Data!$B:$E,3,FALSE) -> #N/A | E19: =VLOOKUP(S19,Data!$B:$E,3,FALSE) -> #N/A | F19: =VLOOKUP(T19,Data!$B:$E,3,FALSE) -> #N/A | G19: =VLOOKUP(U19,Data!$B:$E,3,FALSE) -> #N/A | H19: =VLOOKUP(V19,Data!$B:$E,3,FALSE) -> #N/A | I19: =VLOOKUP(W19,Data!$B:$E,3,FALSE) -> #N/A | J19: =VLOOKUP(X19,Data!$B:$E,3,FALSE) -> #N/A | O19: YZ 450F | P19: A1080 | Q19: A1080.1 | R19: A1080.2 | S19: A1080.8 | T19: A1080.3 | U19: A1080.4 | V19: A1080.5 | W19: A1080.6 | X19: A1080.7
A20: YZ 450 FX | B20: A1085 | C20: =VLOOKUP(Q20,Data!$B:$E,3,FALSE) -> #N/A | D20: =VLOOKUP(R20,Data!$B:$E,3,FALSE) -> #N/A | E20: =VLOOKUP(S20,Data!$B:$E,3,FALSE) -> #N/A | F20: =VLOOKUP(T20,Data!$B:$E,3,FALSE) -> #N/A | G20: =VLOOKUP(U20,Data!$B:$E,3,FALSE) -> #N/A | H20: =VLOOKUP(V20,Data!$B:$E,3,FALSE) -> #N/A | I20: =VLOOKUP(W20,Data!$B:$E,3,FALSE) -> #N/A | J20: =VLOOKUP(X20,Data!$B:$E,3,FALSE) -> #N/A | O20: YZ 450 FX | P20: A1085 | Q20: A1085.1 | R20: A1085.2 | S20: A1085.8 | T20: A1085.3 | U20: A1085.4 | V20: A1085.5 | W20: A1085.6 | X20: A1085.7
A21: =Translation!A50 -> WR 250F | B21: A1090 | C21: =VLOOKUP(Q21,Data!$B:$E,3,FALSE) -> #N/A | D21: =VLOOKUP(R21,Data!$B:$E,3,FALSE) -> #N/A | E21: =VLOOKUP(S21,Data!$B:$E,3,FALSE) -> #N/A | F21: =VLOOKUP(T21,Data!$B:$E,3,FALSE) -> #N/A | G21: =VLOOKUP(U21,Data!$B:$E,3,FALSE) -> #N/A | H21: =VLOOKUP(V21,Data!$B:$E,3,FALSE) -> #N/A | I21: =VLOOKUP(W21,Data!$B:$E,3,FALSE) -> #N/A | J21: =VLOOKUP(X21,Data!$B:$E,3,FALSE) -> #N/A | O21: WR 250F | P21: A1090 | Q21: A1090.1 | R21: A1090.2 | S21: A1090.8 | T21: A1090.3 | U21: A1090.4 | V21: A1090.5 | W21: A1090.6 | X21: A1090.7
A22: WR 450F | B22: A1095 | C22: =VLOOKUP(Q22,Data!$B:$E,3,FALSE) -> #N/A | D22: =VLOOKUP(R22,Data!$B:$E,3,FALSE) -> #N/A | E22: =VLOOKUP(S22,Data!$B:$E,3,FALSE) -> #N/A | F22: =VLOOKUP(T22,Data!$B:$E,3,FALSE) -> #N/A | G22: =VLOOKUP(U22,Data!$B:$E,3,FALSE) -> #N/A | H22: =VLOOKUP(V22,Data!$B:$E,3,FALSE) -> #N/A | I22: =VLOOKUP(W22,Data!$B:$E,3,FALSE) -> #N/A | J22: =VLOOKUP(X22,Data!$B:$E,3,FALSE) -> #N/A | O22: WR 450F | P22: A1095 | Q22: A1095.1 | R22: A1095.2 | S22: A1095.8 | T22: A1095.3 | U22: A1095.4 | V22: A1095.5 | W22: A1095.6 | X22: A1095.7
A23: =Translation!A52 -> TOTAL DE VENDAS - LINHA OFF ROAD | B23: A1100 | C23: =VLOOKUP(Q23,Data!$B:$E,3,FALSE) -> #N/A | D23: =VLOOKUP(R23,Data!$B:$E,3,FALSE) -> #N/A | E23: =VLOOKUP(S23,Data!$B:$E,3,FALSE) -> #N/A | F23: =VLOOKUP(T23,Data!$B:$E,3,FALSE) -> #N/A | G23: =VLOOKUP(U23,Data!$B:$E,3,FALSE) -> #N/A | H23: =VLOOKUP(V23,Data!$B:$E,3,FALSE) -> #N/A | I23: =VLOOKUP(W23,Data!$B:$E,3,FALSE) -> #N/A | J23: =VLOOKUP(X23,Data!$B:$E,3,FALSE) -> #N/A | O23: TOTAL DE VENDAS - LINHA OFF ROAD | P23: A1100 | Q23: A1100.1 | R23: A1100.2 | S23: A1100.8 | T23: A1100.3 | U23: A1100.4 | V23: A1100.5 | W23: A1100.6 | X23: A1100.7
A24: =Translation!A53 -> LINHA 125 cc | B24: =Translation!$G$32 -> CONTA | C24: =Translation!$G$12 -> UNIDADES | D24: =Translation!$G$11 -> RECEITA (SEM IMPOSTOS) | E24: =Translation!$G$33 -> UNIDADES DEVOLVIDAS | F24: =Translation!$G$14 -> DEVOLUÇÃO DE VENDAS | G24: =Translation!$G$3 -> ABAT. E DESCONTO | H24: =Translation!$G$9 -> RECEITA LÍQUIDA | I24: =Translation!$G$2 -> CUSTO | J24: =Translation!$G$5 -> LUCRO BRUTO | O24: LINHA 125 cc | P24: =Translation!$G$32 -> CONTA | Q24: UNITS | R24: SALES | S24: URETURN | T24: SC | U24: DISC | V24: NS | W24: COS | X24: GP
A25: =Translation!A54 -> FACTOR YBR 125i ED | B25: A1110 | C25: =VLOOKUP(Q25,Data!$B:$E,3,FALSE) -> #N/A | D25: =VLOOKUP(R25,Data!$B:$E,3,FALSE) -> #N/A | E25: =VLOOKUP(S25,Data!$B:$E,3,FALSE) -> #N/A | F25: =VLOOKUP(T25,Data!$B:$E,3,FALSE) -> #N/A | G25: =VLOOKUP(U25,Data!$B:$E,3,FALSE) -> #N/A | H25: =VLOOKUP(V25,Data!$B:$E,3,FALSE) -> #N/A | I25: =VLOOKUP(W25,Data!$B:$E,3,FALSE) -> #N/A | J25: =VLOOKUP(X25,Data!$B:$E,3,FALSE) -> #N/A | O25: FACTOR YBR 125i ED | P25: A1110 | Q25: A1110.1 | R25: A1110.2 | S25: A1110.8 | T25: A1110.3 | U25: A1110.4 | V25: A1110.5 | W25: A1110.6 | X25: A1110.7
A26: FLUO ABS | B26: A1111 | C26: =VLOOKUP(Q26,Data!$B:$E,4,FALSE) -> #N/A | D26: =VLOOKUP(R26,Data!$B:$E,4,FALSE) -> #N/A | E26: =VLOOKUP(S26,Data!$B:$E,4,FALSE) -> #N/A | F26: =VLOOKUP(T26,Data!$B:$E,4,FALSE) -> #N/A | G26: =VLOOKUP(U26,Data!$B:$E,4,FALSE) -> #N/A | H26: =VLOOKUP(V26,Data!$B:$E,4,FALSE) -> #N/A | I26: =VLOOKUP(W26,Data!$B:$E,4,FALSE) -> #N/A | J26: =VLOOKUP(X26,Data!$B:$E,4,FALSE) -> #N/A | O26: FLUO ABS | P26: A1111 | Q26: A1111.1 | R26: A1111.2 | S26: A1111.8 | T26: A1111.3 | U26: A1111.4 | V26: A1111.5 | W26: A1111.6 | X26: A1111.7
A27: =Translation!A55 -> TOTAL DE VENDAS - LINHA 125 cc | B27: A1120 | C27: =VLOOKUP(Q27,Data!$B:$E,3,FALSE) -> #N/A | D27: =VLOOKUP(R27,Data!$B:$E,3,FALSE) -> #N/A | E27: =VLOOKUP(S27,Data!$B:$E,3,FALSE) -> #N/A | F27: =VLOOKUP(T27,Data!$B:$E,3,FALSE) -> #N/A | G27: =VLOOKUP(U27,Data!$B:$E,3,FALSE) -> #N/A | H27: =VLOOKUP(V27,Data!$B:$E,3,FALSE) -> #N/A | I27: =VLOOKUP(W27,Data!$B:$E,3,FALSE) -> #N/A | J27: =VLOOKUP(X27,Data!$B:$E,3,FALSE) -> #N/A | O27: TOTAL DE VENDAS - LINHA 125 cc | P27: A1120 | Q27: A1120.1 | R27: A1120.2 | S27: A1120.8 | T27: A1120.3 | U27: A1120.4 | V27: A1120.5 | W27: A1120.6 | X27: A1120.7
A28: =Translation!A56 -> LINHA 150 cc - Street | B28: =Translation!$G$32 -> CONTA | C28: =Translation!$G$12 -> UNIDADES | D28: =Translation!$G$11 -> RECEITA (SEM IMPOSTOS) | E28: =Translation!$G$33 -> UNIDADES DEVOLVIDAS | F28: =Translation!$G$14 -> DEVOLUÇÃO DE VENDAS | G28: =Translation!$G$3 -> ABAT. E DESCONTO | H28: =Translation!$G$9 -> RECEITA LÍQUIDA | I28: =Translation!$G$2 -> CUSTO | J28: =Translation!$G$5 -> LUCRO BRUTO | O28: LINHA 150 cc - Street | P28: =Translation!$G$32 -> CONTA | Q28: UNITS | R28: SALES | S28: URETURN | T28: SC | U28: DISC | V28: NS | W28: COS | X28: GP
A29: =Translation!A57 -> FACTOR 150E | B29: A1130 | C29: =VLOOKUP(Q29,Data!$B:$E,3,FALSE) -> #N/A | D29: =VLOOKUP(R29,Data!$B:$E,3,FALSE) -> #N/A | E29: =VLOOKUP(S29,Data!$B:$E,3,FALSE) -> #N/A | F29: =VLOOKUP(T29,Data!$B:$E,3,FALSE) -> #N/A | G29: =VLOOKUP(U29,Data!$B:$E,3,FALSE) -> #N/A | H29: =VLOOKUP(V29,Data!$B:$E,3,FALSE) -> #N/A | I29: =VLOOKUP(W29,Data!$B:$E,3,FALSE) -> #N/A | J29: =VLOOKUP(X29,Data!$B:$E,3,FALSE) -> #N/A | O29: FACTOR 150E | P29: A1130 | Q29: A1130.1 | R29: A1130.2 | S29: A1130.8 | T29: A1130.3 | U29: A1130.4 | V29: A1130.5 | W29: A1130.6 | X29: A1130.7
A30: =Translation!A58 -> FACTOR 150ED | B30: A1140 | C30: =VLOOKUP(Q30,Data!$B:$E,3,FALSE) -> #N/A | D30: =VLOOKUP(R30,Data!$B:$E,3,FALSE) -> #N/A | E30: =VLOOKUP(S30,Data!$B:$E,3,FALSE) -> #N/A | F30: =VLOOKUP(T30,Data!$B:$E,3,FALSE) -> #N/A | G30: =VLOOKUP(U30,Data!$B:$E,3,FALSE) -> #N/A | H30: =VLOOKUP(V30,Data!$B:$E,3,FALSE) -> #N/A | I30: =VLOOKUP(W30,Data!$B:$E,3,FALSE) -> #N/A | J30: =VLOOKUP(X30,Data!$B:$E,3,FALSE) -> #N/A | O30: FACTOR 150ED | P30: A1140 | Q30: A1140.1 | R30: A1140.2 | S30: A1140.8 | T30: A1140.3 | U30: A1140.4 | V30: A1140.5 | W30: A1140.6 | X30: A1140.7
A31: =Translation!A59 -> YS 150 FAZER SED | B31: A1150 | C31: =VLOOKUP(Q31,Data!$B:$E,3,FALSE) -> #N/A | D31: =VLOOKUP(R31,Data!$B:$E,3,FALSE) -> #N/A | E31: =VLOOKUP(S31,Data!$B:$E,3,FALSE) -> #N/A | F31: =VLOOKUP(T31,Data!$B:$E,3,FALSE) -> #N/A | G31: =VLOOKUP(U31,Data!$B:$E,3,FALSE) -> #N/A | H31: =VLOOKUP(V31,Data!$B:$E,3,FALSE) -> #N/A | I31: =VLOOKUP(W31,Data!$B:$E,3,FALSE) -> #N/A | J31: =VLOOKUP(X31,Data!$B:$E,3,FALSE) -> #N/A | O31: YS 150 FAZER SED | P31: A1150 | Q31: A1150.1 | R31: A1150.2 | S31: A1150.8 | T31: A1150.3 | U31: A1150.4 | V31: A1150.5 | W31: A1150.6 | X31: A1150.7
A32: YZF R15 ABS | B32: A1151 | C32: =VLOOKUP(Q32,Data!$B:$E,4,FALSE) -> #N/A | D32: =VLOOKUP(R32,Data!$B:$E,4,FALSE) -> #N/A | E32: =VLOOKUP(S32,Data!$B:$E,4,FALSE) -> #N/A | F32: =VLOOKUP(T32,Data!$B:$E,4,FALSE) -> #N/A | G32: =VLOOKUP(U32,Data!$B:$E,4,FALSE) -> #N/A | H32: =VLOOKUP(V32,Data!$B:$E,4,FALSE) -> #N/A | I32: =VLOOKUP(W32,Data!$B:$E,4,FALSE) -> #N/A | J32: =VLOOKUP(X32,Data!$B:$E,4,FALSE) -> #N/A | O32: YZF R15 ABS | P32: A1151 | Q32: A1151.1 | R32: A1151.2 | S32: A1151.8 | T32: A1151.3 | U32: A1151.4 | V32: A1151.5 | W32: A1151.6 | X32: A1151.7
A33: FZ15 FAZER ABS | B33: A1152 | C33: =VLOOKUP(Q33,Data!$B:$E,4,FALSE) -> #N/A | D33: =VLOOKUP(R33,Data!$B:$E,4,FALSE) -> #N/A | E33: =VLOOKUP(S33,Data!$B:$E,4,FALSE) -> #N/A | F33: =VLOOKUP(T33,Data!$B:$E,4,FALSE) -> #N/A | G33: =VLOOKUP(U33,Data!$B:$E,4,FALSE) -> #N/A | H33: =VLOOKUP(V33,Data!$B:$E,4,FALSE) -> #N/A | I33: =VLOOKUP(W33,Data!$B:$E,4,FALSE) -> #N/A | J33: =VLOOKUP(X33,Data!$B:$E,4,FALSE) -> #N/A | O33: FZ15 FAZER ABS | P33: A1152 | Q33: A1152.1 | R33: A1152.2 | S33: A1152.8 | T33: A1152.3 | U33: A1152.4 | V33: A1152.5 | W33: A1152.6 | X33: A1152.7
A34: =Translation!A60 -> LINHA 150 cc - On/Off | B34: =Translation!$G$32 -> CONTA | C34: =Translation!$G$12 -> UNIDADES | D34: =Translation!$G$11 -> RECEITA (SEM IMPOSTOS) | E34: =Translation!$G$33 -> UNIDADES DEVOLVIDAS | F34: =Translation!$G$14 -> DEVOLUÇÃO DE VENDAS | G34: =Translation!$G$3 -> ABAT. E DESCONTO | H34: =Translation!$G$9 -> RECEITA LÍQUIDA | I34: =Translation!$G$2 -> CUSTO | J34: =Translation!$G$5 -> LUCRO BRUTO | O34: LINHA 150 cc - On/Off | P34: =Translation!$G$32 -> CONTA | Q34: UNITS | R34: SALES | S34: URETURN | T34: SC | U34: DISC | V34: NS | W34: COS | X34: GP
A35: =Translation!A61 -> XTZ 150 CROSSER E | B35: A1160 | C35: =VLOOKUP(Q35,Data!$B:$E,3,FALSE) -> #N/A | D35: =VLOOKUP(R35,Data!$B:$E,3,FALSE) -> #N/A | E35: =VLOOKUP(S35,Data!$B:$E,3,FALSE) -> #N/A | F35: =VLOOKUP(T35,Data!$B:$E,3,FALSE) -> #N/A | G35: =VLOOKUP(U35,Data!$B:$E,3,FALSE) -> #N/A | H35: =VLOOKUP(V35,Data!$B:$E,3,FALSE) -> #N/A | I35: =VLOOKUP(W35,Data!$B:$E,3,FALSE) -> #N/A | J35: =VLOOKUP(X35,Data!$B:$E,3,FALSE) -> #N/A | O35: XTZ 150 CROSSER E | P35: A1160 | Q35: A1160.1 | R35: A1160.2 | S35: A1160.8 | T35: A1160.3 | U35: A1160.4 | V35: A1160.5 | W35: A1160.6 | X35: A1160.7
A36: =Translation!A62 -> XTZ 150 CROSSER ED | B36: A1170 | C36: =VLOOKUP(Q36,Data!$B:$E,3,FALSE) -> #N/A | D36: =VLOOKUP(R36,Data!$B:$E,3,FALSE) -> #N/A | E36: =VLOOKUP(S36,Data!$B:$E,3,FALSE) -> #N/A | F36: =VLOOKUP(T36,Data!$B:$E,3,FALSE) -> #N/A | G36: =VLOOKUP(U36,Data!$B:$E,3,FALSE) -> #N/A | H36: =VLOOKUP(V36,Data!$B:$E,3,FALSE) -> #N/A | I36: =VLOOKUP(W36,Data!$B:$E,3,FALSE) -> #N/A | J36: =VLOOKUP(X36,Data!$B:$E,3,FALSE) -> #N/A | O36: XTZ 150 CROSSER ED | P36: A1170 | Q36: A1170.1 | R36: A1170.2 | S36: A1170.8 | T36: A1170.3 | U36: A1170.4 | V36: A1170.5 | W36: A1170.6 | X36: A1170.7
A37: XTZ 150 CROSSER S | B37: A1174 | C37: =VLOOKUP(Q37,Data!$B:$E,3,FALSE) -> #N/A | D37: =VLOOKUP(R37,Data!$B:$E,3,FALSE) -> #N/A | E37: =VLOOKUP(S37,Data!$B:$E,3,FALSE) -> #N/A | F37: =VLOOKUP(T37,Data!$B:$E,3,FALSE) -> #N/A | G37: =VLOOKUP(U37,Data!$B:$E,3,FALSE) -> #N/A | H37: =VLOOKUP(V37,Data!$B:$E,3,FALSE) -> #N/A | I37: =VLOOKUP(W37,Data!$B:$E,3,FALSE) -> #N/A | J37: =VLOOKUP(X37,Data!$B:$E,3,FALSE) -> #N/A | O37: XTZ 150 CROSSER S | P37: A1174 | Q37: A1174.1 | R37: A1174.2 | S37: A1174.8 | T37: A1174.3 | U37: A1174.4 | V37: A1174.5 | W37: A1174.6 | X37: A1174.7
A38: XTZ 150 CROSSER Z | B38: A1176 | C38: =VLOOKUP(Q38,Data!$B:$E,3,FALSE) -> #N/A | D38: =VLOOKUP(R38,Data!$B:$E,3,FALSE) -> #N/A | E38: =VLOOKUP(S38,Data!$B:$E,3,FALSE) -> #N/A | F38: =VLOOKUP(T38,Data!$B:$E,3,FALSE) -> #N/A | G38: =VLOOKUP(U38,Data!$B:$E,3,FALSE) -> #N/A | H38: =VLOOKUP(V38,Data!$B:$E,3,FALSE) -> #N/A | I38: =VLOOKUP(W38,Data!$B:$E,3,FALSE) -> #N/A | J38: =VLOOKUP(X38,Data!$B:$E,3,FALSE) -> #N/A | O38: XTZ 150 CROSSER Z | P38: A1176 | Q38: A1176.1 | R38: A1176.2 | S38: A1176.8 | T38: A1176.3 | U38: A1176.4 | V38: A1176.5 | W38: A1176.6 | X38: A1176.7
A39: =Translation!A63 -> TOTAL DE VENDAS - LINHA 150 cc | B39: A1180 | C39: =VLOOKUP(Q39,Data!$B:$E,3,FALSE) -> #N/A | D39: =VLOOKUP(R39,Data!$B:$E,3,FALSE) -> #N/A | E39: =VLOOKUP(S39,Data!$B:$E,3,FALSE) -> #N/A | F39: =VLOOKUP(T39,Data!$B:$E,3,FALSE) -> #N/A | G39: =VLOOKUP(U39,Data!$B:$E,3,FALSE) -> #N/A | H39: =VLOOKUP(V39,Data!$B:$E,3,FALSE) -> #N/A | I39: =VLOOKUP(W39,Data!$B:$E,3,FALSE) -> #N/A | J39: =VLOOKUP(X39,Data!$B:$E,3,FALSE) -> #N/A | O39: TOTAL DE VENDAS - LINHA 150 cc | P39: A1180 | Q39: A1180.1 | R39: A1180.2 | S39: A1180.8 | T39: A1180.3 | U39: A1180.4 | V39: A1180.5 | W39: A1180.6 | X39: A1180.7
A40: =Translation!A64 -> LINHA 250 cc - Street | B40: =Translation!$G$32 -> CONTA | C40: =Translation!$G$12 -> UNIDADES | D40: =Translation!$G$11 -> RECEITA (SEM IMPOSTOS) | E40: =Translation!$G$33 -> UNIDADES DEVOLVIDAS | F40: =Translation!$G$14 -> DEVOLUÇÃO DE VENDAS | G40: =Translation!$G$3 -> ABAT. E DESCONTO | H40: =Translation!$G$9 -> RECEITA LÍQUIDA | I40: =Translation!$G$2 -> CUSTO | J40: =Translation!$G$5 -> LUCRO BRUTO | O40: LINHA 250 cc - Street | P40: =Translation!$G$32 -> CONTA | Q40: UNITS | R40: SALES | S40: URETURN | T40: SC | U40: DISC | V40: NS | W40: COS | X40: GP
A41: =Translation!A65 -> YS 250 FAZER BLUEFLEX | B41: A1190 | C41: =VLOOKUP(Q41,Data!$B:$E,3,FALSE) -> #N/A | D41: =VLOOKUP(R41,Data!$B:$E,3,FALSE) -> #N/A | E41: =VLOOKUP(S41,Data!$B:$E,3,FALSE) -> #N/A | F41: =VLOOKUP(T41,Data!$B:$E,3,FALSE) -> #N/A | G41: =VLOOKUP(U41,Data!$B:$E,3,FALSE) -> #N/A | H41: =VLOOKUP(V41,Data!$B:$E,3,FALSE) -> #N/A | I41: =VLOOKUP(W41,Data!$B:$E,3,FALSE) -> #N/A | J41: =VLOOKUP(X41,Data!$B:$E,3,FALSE) -> #N/A | O41: YS 250 FAZER BLUEFLEX | P41: A1190 | Q41: A1190.1 | R41: A1190.2 | S41: A1190.8 | T41: A1190.3 | U41: A1190.4 | V41: A1190.5 | W41: A1190.6 | X41: A1190.7
A42: FZ25 FAZER ABS | B42: A1195 | C42: =VLOOKUP(Q42,Data!$B:$E,3,FALSE) -> #N/A | D42: =VLOOKUP(R42,Data!$B:$E,3,FALSE) -> #N/A | E42: =VLOOKUP(S42,Data!$B:$E,3,FALSE) -> #N/A | F42: =VLOOKUP(T42,Data!$B:$E,3,FALSE) -> #N/A | G42: =VLOOKUP(U42,Data!$B:$E,3,FALSE) -> #N/A | H42: =VLOOKUP(V42,Data!$B:$E,3,FALSE) -> #N/A | I42: =VLOOKUP(W42,Data!$B:$E,3,FALSE) -> #N/A | J42: =VLOOKUP(X42,Data!$B:$E,3,FALSE) -> #N/A | O42: FZ25 FAZER ABS | P42: A1195 | Q42: A1195.1 | R42: A1195.2 | S42: A1195.8 | T42: A1195.3 | U42: A1195.4 | V42: A1195.5 | W42: A1195.6 | X42: A1195.7
A43: =Translation!A66 -> LINHA 250 cc - On/Off | B43: =Translation!$G$32 -> CONTA | C43: =Translation!$G$12 -> UNIDADES | D43: =Translation!$G$11 -> RECEITA (SEM IMPOSTOS) | E43: =Translation!$G$33 -> UNIDADES DEVOLVIDAS | F43: =Translation!$G$14 -> DEVOLUÇÃO DE VENDAS | G43: =Translation!$G$3 -> ABAT. E DESCONTO | H43: =Translation!$G$9 -> RECEITA LÍQUIDA | I43: =Translation!$G$2 -> CUSTO | J43: =Translation!$G$5 -> LUCRO BRUTO | O43: LINHA 250 cc - On/Off | P43: =Translation!$G$32 -> CONTA | Q43: UNITS | R43: SALES | S43: URETURN | T43: SC | U43: DISC | V43: NS | W43: COS | X43: GP
A44: =Translation!A67 -> XTZ 250 LANDER | B44: A1200 | C44: =VLOOKUP(Q44,Data!$B:$E,3,FALSE) -> #N/A | D44: =VLOOKUP(R44,Data!$B:$E,3,FALSE) -> #N/A | E44: =VLOOKUP(S44,Data!$B:$E,3,FALSE) -> #N/A | F44: =VLOOKUP(T44,Data!$B:$E,3,FALSE) -> #N/A | G44: =VLOOKUP(U44,Data!$B:$E,3,FALSE) -> #N/A | H44: =VLOOKUP(V44,Data!$B:$E,3,FALSE) -> #N/A | I44: =VLOOKUP(W44,Data!$B:$E,3,FALSE) -> #N/A | J44: =VLOOKUP(X44,Data!$B:$E,3,FALSE) -> #N/A | O44: XTZ 250 LANDER | P44: A1200 | Q44: A1200.1 | R44: A1200.2 | S44: A1200.8 | T44: A1200.3 | U44: A1200.4 | V44: A1200.5 | W44: A1200.6 | X44: A1200.7
A45: =Translation!A68 -> XTZ 250 TENERE | B45: A1210 | C45: =VLOOKUP(Q45,Data!$B:$E,3,FALSE) -> #N/A | D45: =VLOOKUP(R45,Data!$B:$E,3,FALSE) -> #N/A | E45: =VLOOKUP(S45,Data!$B:$E,3,FALSE) -> #N/A | F45: =VLOOKUP(T45,Data!$B:$E,3,FALSE) -> #N/A | G45: =VLOOKUP(U45,Data!$B:$E,3,FALSE) -> #N/A | H45: =VLOOKUP(V45,Data!$B:$E,3,FALSE) -> #N/A | I45: =VLOOKUP(W45,Data!$B:$E,3,FALSE) -> #N/A | J45: =VLOOKUP(X45,Data!$B:$E,3,FALSE) -> #N/A | O45: XTZ 250 TENERE | P45: A1210 | Q45: A1210.1 | R45: A1210.2 | S45: A1210.8 | T45: A1210.3 | U45: A1210.4 | V45: A1210.5 | W45: A1210.6 | X45: A1210.7
A46: =Translation!A69 -> TOTAL DE VENDAS - LINHA 250 cc | B46: A1220 | C46: =VLOOKUP(Q46,Data!$B:$E,3,FALSE) -> #N/A | D46: =VLOOKUP(R46,Data!$B:$E,3,FALSE) -> #N/A | E46: =VLOOKUP(S46,Data!$B:$E,3,FALSE) -> #N/A | F46: =VLOOKUP(T46,Data!$B:$E,3,FALSE) -> #N/A | G46: =VLOOKUP(U46,Data!$B:$E,3,FALSE) -> #N/A | H46: =VLOOKUP(V46,Data!$B:$E,3,FALSE) -> #N/A | I46: =VLOOKUP(W46,Data!$B:$E,3,FALSE) -> #N/A | J46: =VLOOKUP(X46,Data!$B:$E,3,FALSE) -> #N/A | O46: TOTAL DE VENDAS - LINHA 250 cc | P46: A1220 | Q46: A1220.1 | R46: A1220.2 | S46: A1220.8 | T46: A1220.3 | U46: A1220.4 | V46: A1220.5 | W46: A1220.6 | X46: A1220.7
A47: =Translation!A70 -> LINHA 320 cc | B47: =Translation!$G$32 -> CONTA | C47: =Translation!$G$12 -> UNIDADES | D47: =Translation!$G$11 -> RECEITA (SEM IMPOSTOS) | E47: =Translation!$G$33 -> UNIDADES DEVOLVIDAS | F47: =Translation!$G$14 -> DEVOLUÇÃO DE VENDAS | G47: =Translation!$G$3 -> ABAT. E DESCONTO | H47: =Translation!$G$9 -> RECEITA LÍQUIDA | I47: =Translation!$G$2 -> CUSTO | J47: =Translation!$G$5 -> LUCRO BRUTO | O47: LINHA 320 cc | P47: =Translation!$G$32 -> CONTA | Q47: UNITS | R47: SALES | S47: URETURN | T47: SC | U47: DISC | V47: NS | W47: COS | X47: GP
A48: =Translation!A71 -> YZF R3 | B48: A1230 | C48: =VLOOKUP(Q48,Data!$B:$E,3,FALSE) -> #N/A | D48: =VLOOKUP(R48,Data!$B:$E,3,FALSE) -> #N/A | E48: =VLOOKUP(S48,Data!$B:$E,3,FALSE) -> #N/A | F48: =VLOOKUP(T48,Data!$B:$E,3,FALSE) -> #N/A | G48: =VLOOKUP(U48,Data!$B:$E,3,FALSE) -> #N/A | H48: =VLOOKUP(V48,Data!$B:$E,3,FALSE) -> #N/A | I48: =VLOOKUP(W48,Data!$B:$E,3,FALSE) -> #N/A | J48: =VLOOKUP(X48,Data!$B:$E,3,FALSE) -> #N/A | O48: YZF R3 | P48: A1230 | Q48: A1230.1 | R48: A1230.2 | S48: A1230.8 | T48: A1230.3 | U48: A1230.4 | V48: A1230.5 | W48: A1230.6 | X48: A1230.7
A49: =Translation!A72 -> YZF R3 ABS | B49: A1240 | C49: =VLOOKUP(Q49,Data!$B:$E,3,FALSE) -> #N/A | D49: =VLOOKUP(R49,Data!$B:$E,3,FALSE) -> #N/A | E49: =VLOOKUP(S49,Data!$B:$E,3,FALSE) -> #N/A | F49: =VLOOKUP(T49,Data!$B:$E,3,FALSE) -> #N/A | G49: =VLOOKUP(U49,Data!$B:$E,3,FALSE) -> #N/A | H49: =VLOOKUP(V49,Data!$B:$E,3,FALSE) -> #N/A | I49: =VLOOKUP(W49,Data!$B:$E,3,FALSE) -> #N/A | J49: =VLOOKUP(X49,Data!$B:$E,3,FALSE) -> #N/A | O49: YZF R3 ABS | P49: A1240 | Q49: A1240.1 | R49: A1240.2 | S49: A1240.8 | T49: A1240.3 | U49: A1240.4 | V49: A1240.5 | W49: A1240.6 | X49: A1240.7
A50: =Translation!A73 -> MT03 | B50: A1250 | C50: =VLOOKUP(Q50,Data!$B:$E,3,FALSE) -> #N/A | D50: =VLOOKUP(R50,Data!$B:$E,3,FALSE) -> #N/A | E50: =VLOOKUP(S50,Data!$B:$E,3,FALSE) -> #N/A | F50: =VLOOKUP(T50,Data!$B:$E,3,FALSE) -> #N/A | G50: =VLOOKUP(U50,Data!$B:$E,3,FALSE) -> #N/A | H50: =VLOOKUP(V50,Data!$B:$E,3,FALSE) -> #N/A | I50: =VLOOKUP(W50,Data!$B:$E,3,FALSE) -> #N/A | J50: =VLOOKUP(X50,Data!$B:$E,3,FALSE) -> #N/A | O50: MT03 | P50: A1250 | Q50: A1250.1 | R50: A1250.2 | S50: A1250.8 | T50: A1250.3 | U50: A1250.4 | V50: A1250.5 | W50: A1250.6 | X50: A1250.7
A51: =Translation!A74 -> MT03 ABS | B51: A1260 | C51: =VLOOKUP(Q51,Data!$B:$E,3,FALSE) -> #N/A | D51: =VLOOKUP(R51,Data!$B:$E,3,FALSE) -> #N/A | E51: =VLOOKUP(S51,Data!$B:$E,3,FALSE) -> #N/A | F51: =VLOOKUP(T51,Data!$B:$E,3,FALSE) -> #N/A | G51: =VLOOKUP(U51,Data!$B:$E,3,FALSE) -> #N/A | H51: =VLOOKUP(V51,Data!$B:$E,3,FALSE) -> #N/A | I51: =VLOOKUP(W51,Data!$B:$E,3,FALSE) -> #N/A | J51: =VLOOKUP(X51,Data!$B:$E,3,FALSE) -> #N/A | O51: MT03 ABS | P51: A1260 | Q51: A1260.1 | R51: A1260.2 | S51: A1260.8 | T51: A1260.3 | U51: A1260.4 | V51: A1260.5 | W51: A1260.6 | X51: A1260.7
A52: =Translation!A75 -> TOTAL DE VENDAS - LINHA 320 cc | B52: A1270 | C52: =VLOOKUP(Q52,Data!$B:$E,3,FALSE) -> #N/A | D52: =VLOOKUP(R52,Data!$B:$E,3,FALSE) -> #N/A | E52: =VLOOKUP(S52,Data!$B:$E,3,FALSE) -> #N/A | F52: =VLOOKUP(T52,Data!$B:$E,3,FALSE) -> #N/A | G52: =VLOOKUP(U52,Data!$B:$E,3,FALSE) -> #N/A | H52: =VLOOKUP(V52,Data!$B:$E,3,FALSE) -> #N/A | I52: =VLOOKUP(W52,Data!$B:$E,3,FALSE) -> #N/A | J52: =VLOOKUP(X52,Data!$B:$E,3,FALSE) -> #N/A | O52: TOTAL DE VENDAS - LINHA 320 cc | P52: A1270 | Q52: A1270.1 | R52: A1270.2 | S52: A1270.8 | T52: A1270.3 | U52: A1270.4 | V52: A1270.5 | W52: A1270.6 | X52: A1270.7
A53: =Translation!A76 -> LINHA > 500 cc | B53: =Translation!$G$32 -> CONTA | C53: =Translation!$G$12 -> UNIDADES | D53: =Translation!$G$11 -> RECEITA (SEM IMPOSTOS) | E53: =Translation!$G$33 -> UNIDADES DEVOLVIDAS | F53: =Translation!$G$14 -> DEVOLUÇÃO DE VENDAS | G53: =Translation!$G$3 -> ABAT. E DESCONTO | H53: =Translation!$G$9 -> RECEITA LÍQUIDA | I53: =Translation!$G$2 -> CUSTO | J53: =Translation!$G$5 -> LUCRO BRUTO | O53: LINHA > 500 cc | P53: =Translation!$G$32 -> CONTA | Q53: UNITS | R53: SALES | S53: URETURN | T53: SC | U53: DISC | V53: NS | W53: COS | X53: GP
A54: =Translation!A77 -> XJ6 N ABS | B54: A1280 | C54: =VLOOKUP(Q54,Data!$B:$E,3,FALSE) -> #N/A | D54: =VLOOKUP(R54,Data!$B:$E,3,FALSE) -> #N/A | E54: =VLOOKUP(S54,Data!$B:$E,3,FALSE) -> #N/A | F54: =VLOOKUP(T54,Data!$B:$E,3,FALSE) -> #N/A | G54: =VLOOKUP(U54,Data!$B:$E,3,FALSE) -> #N/A | H54: =VLOOKUP(V54,Data!$B:$E,3,FALSE) -> #N/A | I54: =VLOOKUP(W54,Data!$B:$E,3,FALSE) -> #N/A | J54: =VLOOKUP(X54,Data!$B:$E,3,FALSE) -> #N/A | O54: XJ6 N ABS | P54: A1280 | Q54: A1280.1 | R54: A1280.2 | S54: A1280.8 | T54: A1280.3 | U54: A1280.4 | V54: A1280.5 | W54: A1280.6 | X54: A1280.7
A55: =Translation!A78 -> XJ6 F ABS | B55: A1290 | C55: =VLOOKUP(Q55,Data!$B:$E,3,FALSE) -> #N/A | D55: =VLOOKUP(R55,Data!$B:$E,3,FALSE) -> #N/A | E55: =VLOOKUP(S55,Data!$B:$E,3,FALSE) -> #N/A | F55: =VLOOKUP(T55,Data!$B:$E,3,FALSE) -> #N/A | G55: =VLOOKUP(U55,Data!$B:$E,3,FALSE) -> #N/A | H55: =VLOOKUP(V55,Data!$B:$E,3,FALSE) -> #N/A | I55: =VLOOKUP(W55,Data!$B:$E,3,FALSE) -> #N/A | J55: =VLOOKUP(X55,Data!$B:$E,3,FALSE) -> #N/A | O55: XJ6 F ABS | P55: A1290 | Q55: A1290.1 | R55: A1290.2 | S55: A1290.8 | T55: A1290.3 | U55: A1290.4 | V55: A1290.5 | W55: A1290.6 | X55: A1290.7
A56: =Translation!A79 -> XT 660R | B56: A1300 | C56: =VLOOKUP(Q56,Data!$B:$E,3,FALSE) -> #N/A | D56: =VLOOKUP(R56,Data!$B:$E,3,FALSE) -> #N/A | E56: =VLOOKUP(S56,Data!$B:$E,3,FALSE) -> #N/A | F56: =VLOOKUP(T56,Data!$B:$E,3,FALSE) -> #N/A | G56: =VLOOKUP(U56,Data!$B:$E,3,FALSE) -> #N/A | H56: =VLOOKUP(V56,Data!$B:$E,3,FALSE) -> #N/A | I56: =VLOOKUP(W56,Data!$B:$E,3,FALSE) -> #N/A | J56: =VLOOKUP(X56,Data!$B:$E,3,FALSE) -> #N/A | O56: XT 660R | P56: A1300 | Q56: A1300.1 | R56: A1300.2 | S56: A1300.8 | T56: A1300.3 | U56: A1300.4 | V56: A1300.5 | W56: A1300.6 | X56: A1300.7
A57: =Translation!A80 -> XT 660Z TENERE ABS | B57: A1310 | C57: =VLOOKUP(Q57,Data!$B:$E,3,FALSE) -> #N/A | D57: =VLOOKUP(R57,Data!$B:$E,3,FALSE) -> #N/A | E57: =VLOOKUP(S57,Data!$B:$E,3,FALSE) -> #N/A | F57: =VLOOKUP(T57,Data!$B:$E,3,FALSE) -> #N/A | G57: =VLOOKUP(U57,Data!$B:$E,3,FALSE) -> #N/A | H57: =VLOOKUP(V57,Data!$B:$E,3,FALSE) -> #N/A | I57: =VLOOKUP(W57,Data!$B:$E,3,FALSE) -> #N/A | J57: =VLOOKUP(X57,Data!$B:$E,3,FALSE) -> #N/A | O57: XT 660Z TENERE ABS | P57: A1310 | Q57: A1310.1 | R57: A1310.2 | S57: A1310.8 | T57: A1310.3 | U57: A1310.4 | V57: A1310.5 | W57: A1310.6 | X57: A1310.7
A58: =Translation!A81 -> MT07 | B58: A1320 | C58: =VLOOKUP(Q58,Data!$B:$E,3,FALSE) -> #N/A | D58: =VLOOKUP(R58,Data!$B:$E,3,FALSE) -> #N/A | E58: =VLOOKUP(S58,Data!$B:$E,3,FALSE) -> #N/A | F58: =VLOOKUP(T58,Data!$B:$E,3,FALSE) -> #N/A | G58: =VLOOKUP(U58,Data!$B:$E,3,FALSE) -> #N/A | H58: =VLOOKUP(V58,Data!$B:$E,3,FALSE) -> #N/A | I58: =VLOOKUP(W58,Data!$B:$E,3,FALSE) -> #N/A | J58: =VLOOKUP(X58,Data!$B:$E,3,FALSE) -> #N/A | O58: MT07 | P58: A1320 | Q58: A1320.1 | R58: A1320.2 | S58: A1320.8 | T58: A1320.3 | U58: A1320.4 | V58: A1320.5 | W58: A1320.6 | X58: A1320.7
A59: =Translation!A82 -> MT07 ABS | B59: A1330 | C59: =VLOOKUP(Q59,Data!$B:$E,3,FALSE) -> #N/A | D59: =VLOOKUP(R59,Data!$B:$E,3,FALSE) -> #N/A | E59: =VLOOKUP(S59,Data!$B:$E,3,FALSE) -> #N/A | F59: =VLOOKUP(T59,Data!$B:$E,3,FALSE) -> #N/A | G59: =VLOOKUP(U59,Data!$B:$E,3,FALSE) -> #N/A | H59: =VLOOKUP(V59,Data!$B:$E,3,FALSE) -> #N/A | I59: =VLOOKUP(W59,Data!$B:$E,3,FALSE) -> #N/A | J59: =VLOOKUP(X59,Data!$B:$E,3,FALSE) -> #N/A | O59: MT07 ABS | P59: A1330 | Q59: A1330.1 | R59: A1330.2 | S59: A1330.8 | T59: A1330.3 | U59: A1330.4 | V59: A1330.5 | W59: A1330.6 | X59: A1330.7
A60: =Translation!A83 -> MT09 | B60: A1340 | C60: =VLOOKUP(Q60,Data!$B:$E,3,FALSE) -> #N/A | D60: =VLOOKUP(R60,Data!$B:$E,3,FALSE) -> #N/A | E60: =VLOOKUP(S60,Data!$B:$E,3,FALSE) -> #N/A | F60: =VLOOKUP(T60,Data!$B:$E,3,FALSE) -> #N/A | G60: =VLOOKUP(U60,Data!$B:$E,3,FALSE) -> #N/A | H60: =VLOOKUP(V60,Data!$B:$E,3,FALSE) -> #N/A | I60: =VLOOKUP(W60,Data!$B:$E,3,FALSE) -> #N/A | J60: =VLOOKUP(X60,Data!$B:$E,3,FALSE) -> #N/A | O60: MT09 | P60: A1340 | Q60: A1340.1 | R60: A1340.2 | S60: A1340.8 | T60: A1340.3 | U60: A1340.4 | V60: A1340.5 | W60: A1340.6 | X60: A1340.7
A61: =Translation!A84 -> MT09 SP | B61: A1350 | C61: =VLOOKUP(Q61,Data!$B:$E,3,FALSE) -> #N/A | D61: =VLOOKUP(R61,Data!$B:$E,3,FALSE) -> #N/A | E61: =VLOOKUP(S61,Data!$B:$E,3,FALSE) -> #N/A | F61: =VLOOKUP(T61,Data!$B:$E,3,FALSE) -> #N/A | G61: =VLOOKUP(U61,Data!$B:$E,3,FALSE) -> #N/A | H61: =VLOOKUP(V61,Data!$B:$E,3,FALSE) -> #N/A | I61: =VLOOKUP(W61,Data!$B:$E,3,FALSE) -> #N/A | J61: =VLOOKUP(X61,Data!$B:$E,3,FALSE) -> #N/A | O61: MT09 SP | P61: A1350 | Q61: A1350.1 | R61: A1350.2 | S61: A1350.8 | T61: A1350.3 | U61: A1350.4 | V61: A1350.5 | W61: A1350.6 | X61: A1350.7
A62: =Translation!A85 -> MT09 TRACER | B62: A1360 | C62: =VLOOKUP(Q62,Data!$B:$E,3,FALSE) -> #N/A | D62: =VLOOKUP(R62,Data!$B:$E,3,FALSE) -> #N/A | E62: =VLOOKUP(S62,Data!$B:$E,3,FALSE) -> #N/A | F62: =VLOOKUP(T62,Data!$B:$E,3,FALSE) -> #N/A | G62: =VLOOKUP(U62,Data!$B:$E,3,FALSE) -> #N/A | H62: =VLOOKUP(V62,Data!$B:$E,3,FALSE) -> #N/A | I62: =VLOOKUP(W62,Data!$B:$E,3,FALSE) -> #N/A | J62: =VLOOKUP(X62,Data!$B:$E,3,FALSE) -> #N/A | O62: MT09 TRACER | P62: A1360 | Q62: A1360.1 | R62: A1360.2 | S62: A1360.8 | T62: A1360.3 | U62: A1360.4 | V62: A1360.5 | W62: A1360.6 | X62: A1360.7
A63: =Translation!A86 -> YZF R1 | B63: A1370 | C63: =VLOOKUP(Q63,Data!$B:$E,3,FALSE) -> #N/A | D63: =VLOOKUP(R63,Data!$B:$E,3,FALSE) -> #N/A | E63: =VLOOKUP(S63,Data!$B:$E,3,FALSE) -> #N/A | F63: =VLOOKUP(T63,Data!$B:$E,3,FALSE) -> #N/A | G63: =VLOOKUP(U63,Data!$B:$E,3,FALSE) -> #N/A | H63: =VLOOKUP(V63,Data!$B:$E,3,FALSE) -> #N/A | I63: =VLOOKUP(W63,Data!$B:$E,3,FALSE) -> #N/A | J63: =VLOOKUP(X63,Data!$B:$E,3,FALSE) -> #N/A | O63: YZF R1 | P63: A1370 | Q63: A1370.1 | R63: A1370.2 | S63: A1370.8 | T63: A1370.3 | U63: A1370.4 | V63: A1370.5 | W63: A1370.6 | X63: A1370.7
A64: =Translation!A87 -> YZF R1M | B64: A1380 | C64: =VLOOKUP(Q64,Data!$B:$E,3,FALSE) -> #N/A | D64: =VLOOKUP(R64,Data!$B:$E,3,FALSE) -> #N/A | E64: =VLOOKUP(S64,Data!$B:$E,3,FALSE) -> #N/A | F64: =VLOOKUP(T64,Data!$B:$E,3,FALSE) -> #N/A | G64: =VLOOKUP(U64,Data!$B:$E,3,FALSE) -> #N/A | H64: =VLOOKUP(V64,Data!$B:$E,3,FALSE) -> #N/A | I64: =VLOOKUP(W64,Data!$B:$E,3,FALSE) -> #N/A | J64: =VLOOKUP(X64,Data!$B:$E,3,FALSE) -> #N/A | O64: YZF R1M | P64: A1380 | Q64: A1380.1 | R64: A1380.2 | S64: A1380.8 | T64: A1380.3 | U64: A1380.4 | V64: A1380.5 | W64: A1380.6 | X64: A1380.7
A65: XT1200Z DX | B65: A1385 | C65: =VLOOKUP(Q65,Data!$B:$E,3,FALSE) -> #N/A | D65: =VLOOKUP(R65,Data!$B:$E,3,FALSE) -> #N/A | E65: =VLOOKUP(S65,Data!$B:$E,3,FALSE) -> #N/A | F65: =VLOOKUP(T65,Data!$B:$E,3,FALSE) -> #N/A | G65: =VLOOKUP(U65,Data!$B:$E,3,FALSE) -> #N/A | H65: =VLOOKUP(V65,Data!$B:$E,3,FALSE) -> #N/A | I65: =VLOOKUP(W65,Data!$B:$E,3,FALSE) -> #N/A | J65: =VLOOKUP(X65,Data!$B:$E,3,FALSE) -> #N/A | O65: XT1200Z DX | P65: A1385 | Q65: A1385.1 | R65: A1385.2 | S65: A1385.8 | T65: A1385.3 | U65: A1385.4 | V65: A1385.5 | W65: A1385.6 | X65: A1385.7
A66: TRACER 900 GT | B66: A1386 | C66: =VLOOKUP(Q66,Data!$B:$E,4,FALSE) -> #N/A | D66: =VLOOKUP(R66,Data!$B:$E,4,FALSE) -> #N/A | E66: =VLOOKUP(S66,Data!$B:$E,4,FALSE) -> #N/A | F66: =VLOOKUP(T66,Data!$B:$E,4,FALSE) -> #N/A | G66: =VLOOKUP(U66,Data!$B:$E,4,FALSE) -> #N/A | H66: =VLOOKUP(V66,Data!$B:$E,4,FALSE) -> #N/A | I66: =VLOOKUP(W66,Data!$B:$E,4,FALSE) -> #N/A | J66: =VLOOKUP(X66,Data!$B:$E,4,FALSE) -> #N/A | O66: TRACER 900 GT | P66: A1386 | Q66: A1386.1 | R66: A1386.2 | S66: A1386.8 | T66: A1386.3 | U66: A1386.4 | V66: A1386.5 | W66: A1386.6 | X66: A1386.7
A67: XTZ690 TENERE | B67: A1387 | C67: =VLOOKUP(Q67,Data!$B:$E,4,FALSE) -> #N/A | D67: =VLOOKUP(R67,Data!$B:$E,4,FALSE) -> #N/A | E67: =VLOOKUP(S67,Data!$B:$E,4,FALSE) -> #N/A | F67: =VLOOKUP(T67,Data!$B:$E,4,FALSE) -> #N/A | G67: =VLOOKUP(U67,Data!$B:$E,4,FALSE) -> #N/A | H67: =VLOOKUP(V67,Data!$B:$E,4,FALSE) -> #N/A | I67: =VLOOKUP(W67,Data!$B:$E,4,FALSE) -> #N/A | J67: =VLOOKUP(X67,Data!$B:$E,4,FALSE) -> #N/A | O67: XTZ690 TENERE | P67: A1387 | Q67: A1387.1 | R67: A1387.2 | S67: A1387.8 | T67: A1387.3 | U67: A1387.4 | V67: A1387.5 | W67: A1387.6 | X67: A1387.7
A68: =Translation!A88 -> TOTAL DE VENDAS - LINHA > 500 cc | B68: A1390 | C68: =VLOOKUP(Q68,Data!$B:$E,3,FALSE) -> #N/A | D68: =VLOOKUP(R68,Data!$B:$E,3,FALSE) -> #N/A | E68: =VLOOKUP(S68,Data!$B:$E,3,FALSE) -> #N/A | F68: =VLOOKUP(T68,Data!$B:$E,3,FALSE) -> #N/A | G68: =VLOOKUP(U68,Data!$B:$E,3,FALSE) -> #N/A | H68: =VLOOKUP(V68,Data!$B:$E,3,FALSE) -> #N/A | I68: =VLOOKUP(W68,Data!$B:$E,3,FALSE) -> #N/A | J68: =VLOOKUP(X68,Data!$B:$E,3,FALSE) -> #N/A | O68: TOTAL DE VENDAS - LINHA > 500 cc | P68: A1390 | Q68: A1390.1 | R68: A1390.2 | S68: A1390.8 | T68: A1390.3 | U68: A1390.4 | V68: A1390.5 | W68: A1390.6 | X68: A1390.7
A69: =Translation!A89 -> TOTAL OUTROS | B69: A1399 | C69: =VLOOKUP(Q69,Data!$B:$E,3,FALSE) -> #N/A | D69: =VLOOKUP(R69,Data!$B:$E,3,FALSE) -> #N/A | E69: =VLOOKUP(S69,Data!$B:$E,3,FALSE) -> #N/A | F69: =VLOOKUP(T69,Data!$B:$E,3,FALSE) -> #N/A | G69: =VLOOKUP(U69,Data!$B:$E,3,FALSE) -> #N/A | H69: =VLOOKUP(V69,Data!$B:$E,3,FALSE) -> #N/A | I69: =VLOOKUP(W69,Data!$B:$E,3,FALSE) -> #N/A | J69: =VLOOKUP(X69,Data!$B:$E,3,FALSE) -> #N/A | O69: TOTAL (NÃO ABERTO) | P69: A1399 | Q69: A1399.1 | R69: A1399.2 | S69: A1399.8 | T69: A1399.3 | U69: A1399.4 | V69: A1399.5 | W69: A1399.6 | X69: A1399.7
A70: =Translation!A90 -> TOTAL DE VENDAS DE NOVOS - MOTOCICLETAS | B70: A1400 | C70: =VLOOKUP(Q70,Data!$B:$E,3,FALSE) -> #N/A | D70: =VLOOKUP(R70,Data!$B:$E,3,FALSE) -> #N/A | E70: =VLOOKUP(S70,Data!$B:$E,3,FALSE) -> #N/A | F70: =VLOOKUP(T70,Data!$B:$E,3,FALSE) -> #N/A | G70: =VLOOKUP(U70,Data!$B:$E,3,FALSE) -> #N/A | H70: =VLOOKUP(V70,Data!$B:$E,3,FALSE) -> #N/A | I70: =VLOOKUP(W70,Data!$B:$E,3,FALSE) -> #N/A | J70: =VLOOKUP(X70,Data!$B:$E,3,FALSE) -> #N/A | O70: TOTAL DE VENDAS DE NOVOS - MOTOCICLETAS | P70: A1400 | Q70: A1400.1 | R70: A1400.2 | S70: A1400.8 | T70: A1400.3 | U70: A1400.4 | V70: A1400.5 | W70: A1400.6 | X70: A1400.7
A71: =Translation!A91 -> LINHA NÁUTICA | B71: =Translation!$G$32 -> CONTA | C71: =Translation!$G$12 -> UNIDADES | D71: =Translation!$G$11 -> RECEITA (SEM IMPOSTOS) | E71: =Translation!$G$33 -> UNIDADES DEVOLVIDAS | F71: =Translation!$G$14 -> DEVOLUÇÃO DE VENDAS | G71: =Translation!$G$3 -> ABAT. E DESCONTO | H71: =Translation!$G$9 -> RECEITA LÍQUIDA | I71: =Translation!$G$2 -> CUSTO | J71: =Translation!$G$5 -> LUCRO BRUTO | O71: LINHA NÁUTICA | P71: =Translation!$G$32 -> CONTA | Q71: UNITS | R71: SALES | S71: URETURN | T71: SC | U71: DISC | V71: NS | W71: COS | X71: GP
A72: =Translation!A92 -> MOTORES | B72: A1700 | C72: =VLOOKUP(Q72,Data!$B:$E,3,FALSE) -> #N/A | D72: =VLOOKUP(R72,Data!$B:$E,3,FALSE) -> #N/A | E72: =VLOOKUP(S72,Data!$B:$E,3,FALSE) -> #N/A | F72: =VLOOKUP(T72,Data!$B:$E,3,FALSE) -> #N/A | G72: =VLOOKUP(U72,Data!$B:$E,3,FALSE) -> #N/A | H72: =VLOOKUP(V72,Data!$B:$E,3,FALSE) -> #N/A | I72: =VLOOKUP(W72,Data!$B:$E,3,FALSE) -> #N/A | J72: =VLOOKUP(X72,Data!$B:$E,3,FALSE) -> #N/A | O72: MOTORES | P72: A1700 | Q72: A1700.1 | R72: A1700.2 | S72: A1700.8 | T72: A1700.3 | U72: A1700.4 | V72: A1700.5 | W72: A1700.6 | X72: A1700.7
A73: =Translation!A93 -> WAVERUNNER | B73: A1710 | C73: =VLOOKUP(Q73,Data!$B:$E,3,FALSE) -> #N/A | D73: =VLOOKUP(R73,Data!$B:$E,3,FALSE) -> #N/A | E73: =VLOOKUP(S73,Data!$B:$E,3,FALSE) -> #N/A | F73: =VLOOKUP(T73,Data!$B:$E,3,FALSE) -> #N/A | G73: =VLOOKUP(U73,Data!$B:$E,3,FALSE) -> #N/A | H73: =VLOOKUP(V73,Data!$B:$E,3,FALSE) -> #N/A | I73: =VLOOKUP(W73,Data!$B:$E,3,FALSE) -> #N/A | J73: =VLOOKUP(X73,Data!$B:$E,3,FALSE) -> #N/A | O73: WAVERUNNER | P73: A1710 | Q73: A1710.1 | R73: A1710.2 | S73: A1710.8 | T73: A1710.3 | U73: A1710.4 | V73: A1710.5 | W73: A1710.6 | X73: A1710.7
A74: =Translation!A94 -> TOTAL DE VENDAS - LINHA NAÚTICA | B74: A1720 | C74: =VLOOKUP(Q74,Data!$B:$E,3,FALSE) -> #N/A | D74: =VLOOKUP(R74,Data!$B:$E,3,FALSE) -> #N/A | E74: =VLOOKUP(S74,Data!$B:$E,3,FALSE) -> #N/A | F74: =VLOOKUP(T74,Data!$B:$E,3,FALSE) -> #N/A | G74: =VLOOKUP(U74,Data!$B:$E,3,FALSE) -> #N/A | H74: =VLOOKUP(V74,Data!$B:$E,3,FALSE) -> #N/A | I74: =VLOOKUP(W74,Data!$B:$E,3,FALSE) -> #N/A | J74: =VLOOKUP(X74,Data!$B:$E,3,FALSE) -> #N/A | O74: TOTAL DE VENDAS - LINHA NAÚTICA | P74: A1720 | Q74: A1720.1 | R74: A1720.2 | S74: A1720.8 | T74: A1720.3 | U74: A1720.4 | V74: A1720.5 | W74: A1720.6 | X74: A1720.7
A75: =Translation!A95 -> LINHA QUADRICICLOS | B75: =Translation!$G$32 -> CONTA | C75: =Translation!$G$12 -> UNIDADES | D75: =Translation!$G$11 -> RECEITA (SEM IMPOSTOS) | E75: =Translation!$G$33 -> UNIDADES DEVOLVIDAS | F75: =Translation!$G$14 -> DEVOLUÇÃO DE VENDAS | G75: =Translation!$G$3 -> ABAT. E DESCONTO | H75: =Translation!$G$9 -> RECEITA LÍQUIDA | I75: =Translation!$G$2 -> CUSTO | J75: =Translation!$G$5 -> LUCRO BRUTO | O75: LINHA QUADRICICLOS | P75: =Translation!$G$32 -> CONTA | Q75: UNITS | R75: SALES | S75: URETURN | T75: SC | U75: DISC | V75: NS | W75: COS | X75: GP
A76: =Translation!A96 -> MODELO 1 | B76: A1800 | C76: =VLOOKUP(Q76,Data!$B:$E,3,FALSE) -> #N/A | D76: =VLOOKUP(R76,Data!$B:$E,3,FALSE) -> #N/A | E76: =VLOOKUP(S76,Data!$B:$E,3,FALSE) -> #N/A | F76: =VLOOKUP(T76,Data!$B:$E,3,FALSE) -> #N/A | G76: =VLOOKUP(U76,Data!$B:$E,3,FALSE) -> #N/A | H76: =VLOOKUP(V76,Data!$B:$E,3,FALSE) -> #N/A | I76: =VLOOKUP(W76,Data!$B:$E,3,FALSE) -> #N/A | J76: =VLOOKUP(X76,Data!$B:$E,3,FALSE) -> #N/A | O76: MODELO 1 | P76: A1800 | Q76: A1800.1 | R76: A1800.2 | S76: A1800.8 | T76: A1800.3 | U76: A1800.4 | V76: A1800.5 | W76: A1800.6 | X76: A1800.7
A77: =Translation!A97 -> MODELO 2 | B77: A1810 | C77: =VLOOKUP(Q77,Data!$B:$E,3,FALSE) -> #N/A | D77: =VLOOKUP(R77,Data!$B:$E,3,FALSE) -> #N/A | E77: =VLOOKUP(S77,Data!$B:$E,3,FALSE) -> #N/A | F77: =VLOOKUP(T77,Data!$B:$E,3,FALSE) -> #N/A | G77: =VLOOKUP(U77,Data!$B:$E,3,FALSE) -> #N/A | H77: =VLOOKUP(V77,Data!$B:$E,3,FALSE) -> #N/A | I77: =VLOOKUP(W77,Data!$B:$E,3,FALSE) -> #N/A | J77: =VLOOKUP(X77,Data!$B:$E,3,FALSE) -> #N/A | O77: MODELO 2 | P77: A1810 | Q77: A1810.1 | R77: A1810.2 | S77: A1810.8 | T77: A1810.3 | U77: A1810.4 | V77: A1810.5 | W77: A1810.6 | X77: A1810.7
A78: =Translation!A98 -> MODELO 3 | B78: A1820 | C78: =VLOOKUP(Q78,Data!$B:$E,3,FALSE) -> #N/A | D78: =VLOOKUP(R78,Data!$B:$E,3,FALSE) -> #N/A | E78: =VLOOKUP(S78,Data!$B:$E,3,FALSE) -> #N/A | F78: =VLOOKUP(T78,Data!$B:$E,3,FALSE) -> #N/A | G78: =VLOOKUP(U78,Data!$B:$E,3,FALSE) -> #N/A | H78: =VLOOKUP(V78,Data!$B:$E,3,FALSE) -> #N/A | I78: =VLOOKUP(W78,Data!$B:$E,3,FALSE) -> #N/A | J78: =VLOOKUP(X78,Data!$B:$E,3,FALSE) -> #N/A | O78: MODELO 3 | P78: A1820 | Q78: A1820.1 | R78: A1820.2 | S78: A1820.8 | T78: A1820.3 | U78: A1820.4 | V78: A1820.5 | W78: A1820.6 | X78: A1820.7
A79: =Translation!A99 -> TOTAL DE VENDAS - LINHA QUADRICICLOS | B79: A1830 | C79: =VLOOKUP(Q79,Data!$B:$E,3,FALSE) -> #N/A | D79: =VLOOKUP(R79,Data!$B:$E,3,FALSE) -> #N/A | E79: =VLOOKUP(S79,Data!$B:$E,3,FALSE) -> #N/A | F79: =VLOOKUP(T79,Data!$B:$E,3,FALSE) -> #N/A | G79: =VLOOKUP(U79,Data!$B:$E,3,FALSE) -> #N/A | H79: =VLOOKUP(V79,Data!$B:$E,3,FALSE) -> #N/A | I79: =VLOOKUP(W79,Data!$B:$E,3,FALSE) -> #N/A | J79: =VLOOKUP(X79,Data!$B:$E,3,FALSE) -> #N/A | O79: TOTAL DE VENDAS - LINHA QUADRICICLOS | P79: A1830 | Q79: A1830.1 | R79: A1830.2 | S79: A1830.8 | T79: A1830.3 | U79: A1830.4 | V79: A1830.5 | W79: A1830.6 | X79: A1830.7
A80: =Translation!A100 -> TOTAL DE VENDAS DE VEÍCULOS | B80: A1840 | C80: =VLOOKUP(Q80,Data!$B:$E,3,FALSE) -> #N/A | D80: =VLOOKUP(R80,Data!$B:$E,3,FALSE) -> #N/A | E80: =VLOOKUP(S80,Data!$B:$E,3,FALSE) -> #N/A | F80: =VLOOKUP(T80,Data!$B:$E,3,FALSE) -> #N/A | G80: =VLOOKUP(U80,Data!$B:$E,3,FALSE) -> #N/A | H80: =VLOOKUP(V80,Data!$B:$E,3,FALSE) -> #N/A | I80: =VLOOKUP(W80,Data!$B:$E,3,FALSE) -> #N/A | J80: =VLOOKUP(X80,Data!$B:$E,3,FALSE) -> #N/A | O80: TOTAL DE VENDAS DE VEÍCULOS | P80: A1840 | Q80: A1840.1 | R80: A1840.2 | S80: A1840.8 | T80: A1840.3 | U80: A1840.4 | V80: A1840.5 | W80: A1840.6 | X80: A1840.7
A81: =Translation!A101 -> OUTRAS RECEITAS OPERACIONAIS | B81: =Translation!$G$32 -> CONTA | C81: =Translation!$G$1 -> VALOR | O81: OUTRAS RECEITAS OPERACIONAIS | P81: =Translation!$G$32 -> CONTA | Q81: =Translation!$G$1 -> VALOR
A82: =Translation!A102 -> INCENTIVOS DE VAREJO | B82: A3000 | C82: =VLOOKUP(Q82,Data!$B:$E,3,FALSE) -> #N/A | O82: INCENTIVOS DE VAREJO | P82: A3000 | Q82: A3000.1
A83: =Translation!A103 -> BONIFICAÇÕES 1 | B83: A3010 | C83: =VLOOKUP(Q83,Data!$B:$E,3,FALSE) -> #N/A | O83: BONIFICAÇÕES 1 | P83: A3010 | Q83: A3010.1
A84: =Translation!A104 -> BONIFICAÇÕES 2 | B84: A3020 | C84: =VLOOKUP(Q84,Data!$B:$E,3,FALSE) -> #N/A | O84: BONIFICAÇÕES 2 | P84: A3020 | Q84: A3020.1
A85: =Translation!A105 -> COMISSÕES DIVERSAS | B85: A3030 | C85: =VLOOKUP(Q85,Data!$B:$E,3,FALSE) -> #N/A | O85: COMISSÕES DIVERSAS | P85: A3030 | Q85: A3030.1
A86: =Translation!A106 -> OUTRAS RECEITAS | B86: A3040 | C86: =VLOOKUP(Q86,Data!$B:$E,3,FALSE) -> #N/A | O86: OUTRAS RECEITAS | P86: A3040 | Q86: A3040.1
A87: =Translation!A107 -> TOTAL DE OUTRAS RECEITAS OPERACIONAIS | B87: A3090 | C87: =VLOOKUP(Q87,Data!$B:$E,3,FALSE) -> #N/A | O87: TOTAL DE OUTRAS RECEITAS OPERACIONAIS | P87: A3090 | Q87: A3090.1
A88: =Translation!A108 -> DESPESAS VARIÁVEIS | B88: =Translation!$G$32 -> CONTA | C88: =Translation!$G$1 -> VALOR | O88: DESPESAS VARIÁVEIS | P88: =Translation!$G$32 -> CONTA | Q88: =Translation!$G$1 -> VALOR
A89: =Translation!A109 -> COMISSÕES SOBRE VENDAS | B89: A3100 | C89: =VLOOKUP(Q89,Data!$B:$E,3,FALSE) -> #N/A | O89: COMISSÕES SOBRE VENDAS | P89: A3100 | Q89: A3100.1
A90: =Translation!A110 -> ENCARGOS SOBRE COMISSÕES (-) | B90: A3110 | C90: =VLOOKUP(Q90,Data!$B:$E,3,FALSE) -> #N/A | O90: ENCARGOS SOBRE COMISSÕES (-) | P90: A3110 | Q90: A3110.1
A91: =Translation!A111 -> OUTRAS DESPESAS | B91: A3120 | C91: =VLOOKUP(Q91,Data!$B:$E,3,FALSE) -> #N/A | O91: OUTRAS DESPESAS | P91: A3120 | Q91: A3120.1
A92: =Translation!A112 -> TOTAL DE DESPESAS VARIÁVEIS | B92: A3130 | C92: =VLOOKUP(Q92,Data!$B:$E,3,FALSE) -> #N/A | O92: TOTAL DE DESPESAS VARIÁVEIS | P92: A3130 | Q92: A3130.1
A93: =Translation!A113 -> MARGEM DE CONTRIBUIÇÃO | B93: =Translation!$G$32 -> CONTA | C93: =Translation!$G$1 -> VALOR | O93: MARGEM DE CONTRIBUIÇÃO | P93: =Translation!$G$32 -> CONTA | Q93: =Translation!$G$1 -> VALOR
A94: =Translation!A114 -> MARGEM DE CONTRIBUIÇÃO | B94: A3500 | C94: =VLOOKUP(Q94,Data!$B:$E,3,FALSE) -> #N/A | O94: MARGEM DE CONTRIBUIÇÃO | P94: A3500 | Q94: A3500.1
A95: =Translation!A115 -> DESPESAS | B95: =Translation!$G$32 -> CONTA | C95: =Translation!$G$1 -> VALOR | O95: DESPESAS | P95: =Translation!$G$32 -> CONTA | Q95: =Translation!$G$1 -> VALOR
A96: =Translation!A116 -> TOTAL DE DESPESAS COM PESSOAL (A) | B96: A4090 | C96: =VLOOKUP(Q96,Data!$B:$E,3,FALSE) -> #N/A | O96: TOTAL DE DESPESAS COM PESSOAL (A) | P96: A4090 | Q96: A4090.1
A97: =Translation!A117 -> TOTAL DE DESPESAS COM ESTRUTURA - IMÓVEIS (B) | B97: A4170 | C97: =VLOOKUP(Q97,Data!$B:$E,3,FALSE) -> #N/A | O97: TOTAL DE DESPESAS COM ESTRUTURA - IMÓVEIS (B) | P97: A4170 | Q97: A4170.1
A98: =Translation!A118 -> TOTAL DE DESPESAS GERAIS (C) | B98: A4370 | C98: =VLOOKUP(Q98,Data!$B:$E,3,FALSE) -> #N/A | O98: TOTAL DE DESPESAS GERAIS (C) | P98: A4370 | Q98: A4370.1
A99: =Translation!A119 -> TOTAL DE DESPESAS FIXAS (A+B+C) | B99: A4380 | C99: =VLOOKUP(Q99,Data!$B:$E,3,FALSE) -> #N/A | O99: TOTAL DE DESPESAS OPERACIONAIS (A + B + C) | P99: A4380 | Q99: A4380.1
A100: =Translation!A120 -> LUCRO / PREJUÍZO OPERACIONAL | B100: =Translation!$G$32 -> CONTA | C100: =Translation!$G$1 -> VALOR | O100: LUCRO / PREJUÍZO OPERACIONAL | P100: =Translation!$G$32 -> CONTA | Q100: =Translation!$G$1 -> VALOR
...

Sheet Data
C1: Dealer Name | D1: Nippon Motos - Bragança | E1: Nippon Motos - Bragança | G1: LanguageID | H1: 1 | I1: =IF(G2=1,J1,K1) -> Jan | J1: Jan | K1: Jan | N1: 1 | O1: BAC | P1: 8 | Q1: CITY_NM
C2: Location | H2: 2 | I2: =IF(G3=1,J2,K2) -> Fev | J2: Feb | K2: Fev | N2: 2 | O2: End Month | P2: 9 | Q2: POSTL_STATE_CD
C3: City | D3: BRAGANCA PAULISTA | H3: 3 | I3: =IF(G4=1,J3,K3) -> Mar | J3: Mar | K3: Mar | N3: 3 | O3: End Year | P3: 10 | Q3: POSTL_CD
C4: BAC | D4: 1696-01 | E4: 1696-01 | H4: 4 | I4: =IF(G5=1,J4,K4) -> Abr | J4: Apr | K4: Abr | N4: 4 | O4: Dealer Name | P4: 11 | Q4: GMBA_ACTVTN_DT
C5: State | H5: 5 | I5: =IF(G6=1,J5,K5) -> Mai | J5: May | K5: Mai | N5: 5 | O5: ADDR_LINE_1_TXT | P5: 15 | Q5: Dealer'
C6: End Month / End Year | D6: 4 | E6: 2026 | H6: 6 | I6: =IF(G7=1,J6,K6) -> Jun | J6: Jun | K6: Jun | N6: 6 | O6: ADDR_LINE_2_TXT | P6: 16 | Q6: CountryCode
C7: Dealer/Composite | D7: Dealer | H7: 7 | I7: =IF(G8=1,J7,K7) -> Jul | J7: Jul | K7: Jul | P7: 17 | Q7: Location
C8: Country Code | H8: 8 | I8: =IF(G9=1,J8,K8) -> Ago | J8: Aug | K8: Ago | P8: 18 | Q8: @PhaseID
C9: Submission Status | H9: 9 | I9: =IF(G10=1,J9,K9) -> Set | J9: Sep | K9: Set
C10: Reserved | H10: 10 | I10: =IF(G11=1,J10,K10) -> Out | J10: Oct | K10: Out
H11: 11 | I11: =IF(G12=1,J11,K11) -> Nov | J11: Nov | K11: Nov
H12: 12 | I12: =IF(G13=1,J12,K12) -> Dez | J12: Dec | K12: Dez
A13: System Assigned # | B13: Local Acct # | C13: Description | D13: Month Data | E13: YTD Data
A14: 1 | B14: A1000.1 | C14: NEO 125 - UNIDADES | D14: 0 | E14: 0
A15: 2 | B15: A1000.2 | C15: NEO 125 - RECEITA | D15: 0 | E15: 0
A16: 3 | B16: A1000.3 | C16: NEO 125 - DEVOLUÇÃO DE VENDAS | D16: 0 | E16: 0
A17: 4 | B17: A1000.4 | C17: NEO 125 - ABAT. E DESCONTO | D17: 0 | E17: 0
A18: 5 | B18: A1000.5 | C18: NEO 125 - VENDA LÍQUIDA | D18: 0 | E18: 0
A19: 6 | B19: A1000.6 | C19: NEO 125 - CUSTO | D19: 0 | E19: 0
A20: 7 | B20: A1000.7 | C20: NEO 125 - LUCRO BRUTO | D20: 0 | E20: 0
A21: 8 | B21: A1010.1 | C21: NMAX 160 ABS - UNIDADES | D21: 0 | E21: 0
A22: 9 | B22: A1010.2 | C22: NMAX 160 ABS - RECEITA | D22: 0 | E22: 0
A23: 10 | B23: A1010.3 | C23: NMAX 160 ABS - DEVOLUÇÃO DE VENDAS | D23: 0 | E23: 0
A24: 11 | B24: A1010.4 | C24: NMAX 160 ABS - ABAT. E DESCONTO | D24: 0 | E24: 0
A25: 12 | B25: A1010.5 | C25: NMAX 160 ABS - VENDA LÍQUIDA | D25: 0 | E25: 0
... A1434: 10005 | B1434: DLRMTHS | C1434: Dealer Report Period | D1434: 1 | E1434: 4

Sheet Translation
A1: =IF(LanguageID=1,B1,C1) -> VENDA DE NOVOS | B1: New Sales | C1: VENDA DE NOVOS | F1: =Translation!$G$1 -> VALOR | G1: =IF(LanguageID=1,H1,I1) -> VALOR | H1: AMOUNT | I1: VALOR
A2: =IF(LanguageID=1,B2,C2) -> VENDAS DE USADOS | B2: Used Sales | C2: VENDAS DE USADOS | F2: COS | G2: =IF(LanguageID=1,H2,I2) -> CUSTO | H2: COST OF SALES | I2: CUSTO
A3: =IF(LanguageID=1,B3,C3) -> PEÇAS E ACESSÓRIOS | B3: Parts | C3: PEÇAS E ACESSÓRIOS | F3: DISC | G3: =IF(LanguageID=1,H3,I3) -> ABAT. E DESCONTO | H3: DISCOUNT | I3: ABAT. E DESCONTO
A4: =IF(LanguageID=1,B4,C4) -> SERVIÇO | B4: Service | C4: SERVIÇO | F4: DP | G4: =IF(LanguageID=1,H4,I4) -> DIRECT PROFIT | H4: DIRECT PROFIT | I4: DIRECT PROFIT
A5: =IF(LanguageID=1,B5,C5) -> F & I | B5: F & I | C5: F & I | F5: GP | G5: =IF(LanguageID=1,H5,I5) -> LUCRO BRUTO | H5: GROSS PROFIT | I5: LUCRO BRUTO
A6: =IF(LanguageID=1,B6,C6) -> ADMIN | B6: Admin | C6: ADMIN | F6: HC | G6: =IF(LanguageID=1,H6,I6) -> NUN. FUNCIONÁRIOS | H6: HEADCOUNT | I6: NUN. FUNCIONÁRIOS
A7: =IF(LanguageID=1,B7,C7) -> BALANÇO | B7: Balance Sheet | C7: BALANÇO | F7: HOURS | G7: =IF(LanguageID=1,H7,I7) -> HORAS | H7: HOURS | I7: HORAS
F8: JC | G8: =IF(LanguageID=1,H8,I8) -> O.S. | H8: JOB CARDS | I8: O.S.
F9: NS | G9: =IF(LanguageID=1,H9,I9) -> RECEITA LÍQUIDA | H9: NET SALES | I9: RECEITA LÍQUIDA
F10: RR | G10: =IF(LanguageID=1,H10,I10) -> TARIFA REAL | H10: RECOVERY RATE | I10: TARIFA REAL
F11: SALES | G11: =IF(LanguageID=1,H11,I11) -> RECEITA (SEM IMPOSTOS) | H11: SALES | I11: RECEITA (SEM IMPOSTOS)
F12: UNITS | G12: =IF(LanguageID=1,H12,I12) -> UNIDADES | H12: UNITS | I12: UNIDADES
F13: VALUE | G13: =IF(LanguageID=1,H13,I13) -> VALOR | H13: VALUE | I13: VALOR
F14: SC | G14: =IF(LanguageID=1,H14,I14) -> DEVOLUÇÃO DE VENDAS | H14: SALE CANCELED | I14: DEVOLUÇÃO DE VENDAS
F15: AREA | G15: =IF(LanguageID=1,H15,I15) -> ÁREA | H15: AREA | I15: ÁREA
F16: NNEW | G16: =IF(LanguageID=1,H16,I16) -> NOVOS | H16: NEW | I16: NOVOS
F17: NUSED | G17: =IF(LanguageID=1,H17,I17) -> USADOS | H17: USED | I17: USADOS
B18: EN | C18: PT | F18: NF&I | G18: =IF(LanguageID=1,H18,I18) -> F & I | H18: F & I | I18: F & I
A19: =IF(LanguageID=1,B19,C19) -> Localização: | B19: Location: | C19: Localização: | F19: NPARTS | G19: =IF(LanguageID=1,H19,I19) -> PEÇAS E ACESS. | H19: PARTS | I19: PEÇAS E ACESS.
A20: =IF(LanguageID=1,B20,C20) -> Concessionário: | B20: =IF(Data!D7="Composite", "Composite: ", "Dealer: ") -> Dealer: | C20: =IF(Data!D7="Composite", "Comparativo: ", "Concessionário: ") -> Concessionário: | F20: NSERV | G20: =IF(LanguageID=1,H20,I20) -> SERVIÇO | H20: SERVICES | I20: SERVIÇO
A21: =IF(LanguageID=1,B21,C21) -> Período: | B21: Report Period Ending: | C21: Período: | F21: NADM | G21: =IF(LanguageID=1,H21,I21) -> ADM | H21: ADMIN | I21: ADM
A22: =IF(LanguageID=1,B22,C22) -> DRE YAMAHA BMI - Acumulado | B22: YAMAHA BMI Financial Statement - YTD | C22: DRE YAMAHA BMI - Acumulado | F22: NTOT | G22: =IF(LanguageID=1,H22,I22) -> TOTAL | H22: TOTAL | I22: TOTAL
A23: =IF(LanguageID=1,B23,C23) -> DRE YAMAHA BMI - Mês | B23: YAMAHA BMI Financial Statement - MTH | C23: DRE YAMAHA BMI - Mês | F23: ANEW | G23: =IF(LanguageID=1,H23,I23) -> NOVOS | H23: NEW | I23: NOVOS
F24: AUSED | G24: =IF(LanguageID=1,H24,I24) -> USADOS | H24: USED | I24: USADOS
F25: AF&I | G25: =IF(LanguageID=1,H25,I25) -> F & I | H25: F & I | I25: F & I
F26: APARTS | G26: =IF(LanguageID=1,H26,I26) -> PEÇAS E ACESS. | H26: PARTS | I26: PEÇAS E ACESS.
F27: ASERV | G27: =IF(LanguageID=1,H27,I27) -> SERVIÇO | H27: SERVICES | I27: SERVIÇO
F28: AADM | G28: =IF(LanguageID=1,H28,I28) -> ADM | H28: ADMIN | I28: ADM
F29: ATOT | G29: =IF(LanguageID=1,H29,I29) -> TOTAL | H29: TOTAL | I29: TOTAL
F30: =Translation!$G$30 -> ESTOQUE FINAL | G30: =IF(LanguageID=1,H30,I30) -> ESTOQUE FINAL | H30: FINAL STOCK | I30: ESTOQUE FINAL
F31: SHARE | G31: =IF(LanguageID=1,H31,I31) -> % | H31: EQUITY INTEREST (%) | I31: %
F32: =Translation!$G$32 -> CONTA | G32: =IF(LanguageID=1,H32,I32) -> CONTA | H32: ACCT | I32: CONTA
F33: URETURN | G33: UNIDADES DEVOLVIDAS | H33: RETURNED UNITS | I33: UNIDADES DEVOLVIDAS
A35: =IF(LanguageID=1,B35,C35) -> LINHA SCOOTER <200 cc | B35: LINE SCOOTER <200 cc | C35: LINHA SCOOTER <200 cc
A36: =IF(LanguageID=1,B36,C36) -> NEO 125 | B36: NEO 125 | C36: NEO 125
A37: =IF(LanguageID=1,B37,C37) -> NMAX 160 ABS | B37: NMAX 160 ABS | C37: NMAX 160 ABS
A38: =IF(LanguageID=1,B38,C38) -> LINHA SCOOTER >200 cc | B38: LINE SCOOTER >200 cc | C38: LINHA SCOOTER >200 cc
A39: =IF(LanguageID=1,B39,C39) -> TMAX 530 | B39: TMAX 530 | C39: TMAX 530
A40: =IF(LanguageID=1,B40,C40) -> TOTAL DE VENDAS - SCOOTER | B40: TOTAL SALES - SCOOTER | C40: TOTAL DE VENDAS - SCOOTER
A41: =IF(LanguageID=1,B41,C41) -> LINHA OFF ROAD | B41: LINE OFF ROAD | C41: LINHA OFF ROAD
A42: =IF(LanguageID=1,B42,C42) -> TTR 230 | B42: TTR 230 | C42: TTR 230
A43: =IF(LanguageID=1,B43,C43) -> YZ 85LW | B43: YZ 85LW | C43: YZ 85LW
A44: =IF(LanguageID=1,B44,C44) -> YZ 250 | B44: YZ 250 | C44: YZ 250
A45: =IF(LanguageID=1,B45,C45) -> YZ 250F | B45: YZ 250F | C45: YZ 250F
A46: =IF(LanguageID=1,B46,C46) -> YZ 250FX | B46: YZ 250FX | C46: YZ 250FX
... A540: =IF(LanguageID=1,B540,C540) -> TOTAL OUTROS | B540: TOTAL OTHERS | C540: TOTAL OUTROS
